{
"metadata": {
    "version": {
        "essentia": "2.1-beta6-dev",
        "essentia_git_sha": "v2.1_beta5-778-gc9eadba6",
        "extractor": "music 2.0"
    },
    "audio_properties": {
        "analysis": {
            "equal_loudness": 0,
            "length": 7.99997711182,
            "sample_rate": 44100,
            "start_time": 0,
            "downmix": "mix"
        },
        "bit_rate": 128000,
        "length": 8,
        "lossless": 0,
        "number_channels": 2,
        "replay_gain": -4.42827033997,
        "sample_rate": 48000,
        "codec": "mp3",
        "md5_encoded": "2b6720ac307c5db9ffb014a493019eed"
    },
    "tags": {
        "file_name": "jacopastorius-fullalbum2.mp3",
        "encoding": ["Lavf59.16.100"]
    }
},
"lowlevel": {
    "average_loudness": 0.982091963291,
    "barkbands_crest": {
        "dmean": 3.89200115204,
        "dmean2": 6.06359910965,
        "dvar": 8.57402515411,
        "dvar2": 19.5367298126,
        "max": 24.8639030457,
        "mean": 14.5986833572,
        "median": 13.823091507,
        "min": 4.90953063965,
        "stdev": 4.7239151001,
        "var": 22.315372467
    },
    "barkbands_flatness_db": {
        "dmean": 0.0506120659411,
        "dmean2": 0.0776001065969,
        "dvar": 0.0023068820592,
        "dvar2": 0.00450219772756,
        "max": 0.555715858936,
        "mean": 0.344973891973,
        "median": 0.334263950586,
        "min": 0.0715089216828,
        "stdev": 0.0830903053284,
        "var": 0.00690399855375
    },
    "barkbands_kurtosis": {
        "dmean": 10.8886451721,
        "dmean2": 17.3494224548,
        "dvar": 246.036117554,
        "dvar2": 615.285705566,
        "max": 139.041854858,
        "mean": 16.6647472382,
        "median": 10.7296819687,
        "min": -0.448843002319,
        "stdev": 19.0221767426,
        "var": 361.843200684
    },
    "barkbands_skewness": {
        "dmean": 1.00074768066,
        "dmean2": 1.56059706211,
        "dvar": 0.910379767418,
        "dvar2": 2.0794775486,
        "max": 8.86487197876,
        "mean": 2.51105713844,
        "median": 2.36430549622,
        "min": -1.89582002163,
        "stdev": 1.50690245628,
        "var": 2.27075505257
    },
    "barkbands_spread": {
        "dmean": 1.43589603901,
        "dmean2": 2.21265411377,
        "dvar": 3.08737945557,
        "dvar2": 4.9729347229,
        "max": 26.9381523132,
        "mean": 3.23998212814,
        "median": 2.50701355934,
        "min": 0.311704397202,
        "stdev": 2.73188066483,
        "var": 7.46317195892
    },
    "dissonance": {
        "dmean": 0.0484693236649,
        "dmean2": 0.0780992209911,
        "dvar": 0.00153011770453,
        "dvar2": 0.00410509994254,
        "max": 0.498542070389,
        "mean": 0.394208163023,
        "median": 0.397704333067,
        "min": 0.252452164888,
        "stdev": 0.0548701174557,
        "var": 0.00301072979346
    },
    "dynamic_complexity": 3.24303603172,
    "erbbands_crest": {
        "dmean": 3.23930740356,
        "dmean2": 5.09362745285,
        "dvar": 7.35000658035,
        "dvar2": 15.5574407578,
        "max": 29.4893398285,
        "mean": 12.175699234,
        "median": 10.8057565689,
        "min": 3.57256937027,
        "stdev": 5.29251813889,
        "var": 28.0107498169
    },
    "erbbands_flatness_db": {
        "dmean": 0.0312277097255,
        "dmean2": 0.0446435511112,
        "dvar": 0.000674299255479,
        "dvar2": 0.00136900541838,
        "max": 0.414642214775,
        "mean": 0.249784275889,
        "median": 0.249460458755,
        "min": 0.0928289741278,
        "stdev": 0.0505844503641,
        "var": 0.00255878665484
    },
    "erbbands_kurtosis": {
        "dmean": 3.47308158875,
        "dmean2": 5.20117807388,
        "dvar": 19.5908527374,
        "dvar2": 46.995716095,
        "max": 49.9745025635,
        "mean": 4.62005281448,
        "median": 2.58677697182,
        "min": -1.26666140556,
        "stdev": 6.12432003021,
        "var": 37.5072975159
    },
    "erbbands_skewness": {
        "dmean": 0.639464497566,
        "dmean2": 0.935007214546,
        "dvar": 0.286991596222,
        "dvar2": 0.646660089493,
        "max": 4.74403762817,
        "mean": 1.31567466259,
        "median": 1.28138709068,
        "min": -0.634387016296,
        "stdev": 0.942973911762,
        "var": 0.889199852943
    },
    "erbbands_spread": {
        "dmean": 4.6483874321,
        "dmean2": 6.75590467453,
        "dvar": 18.6524543762,
        "dvar2": 38.4568557739,
        "max": 43.2515525818,
        "mean": 15.9649209976,
        "median": 15.1863899231,
        "min": 1.09537351131,
        "stdev": 7.69650506973,
        "var": 59.2361869812
    },
    "hfc": {
        "dmean": 4.84771490097,
        "dmean2": 7.60075426102,
        "dvar": 63.5827484131,
        "dvar2": 164.059417725,
        "max": 49.9414596558,
        "mean": 6.69720077515,
        "median": 4.1220741272,
        "min": 1.21737375124e-16,
        "stdev": 8.31892967224,
        "var": 69.2045898438
    },
    "loudness_ebu128": {
        "integrated": -17.9239940643,
        "loudness_range": 0.772861480713,
        "momentary": {
            "dmean": 0.703296840191,
            "dmean2": 0.811403274536,
            "dvar": 0.58222258091,
            "dvar2": 0.45661136508,
            "max": -16.2664775848,
            "mean": -18.6076068878,
            "median": -17.5794372559,
            "min": -30.6073513031,
            "stdev": 2.80594968796,
            "var": 7.87335300446
        },
        "short_term": {
            "dmean": 0.124724842608,
            "dmean2": 0.170600309968,
            "dvar": 0.0106014683843,
            "dvar2": 0.0199531335384,
            "max": -17.1662025452,
            "mean": -17.6014232635,
            "median": -17.4910736084,
            "min": -18.5016708374,
            "stdev": 0.308203279972,
            "var": 0.0949892625213
        }
    },
    "melbands_crest": {
        "dmean": 4.59840345383,
        "dmean2": 7.13842773438,
        "dvar": 11.4119520187,
        "dvar2": 24.959936142,
        "max": 33.671257019,
        "mean": 19.4832267761,
        "median": 18.9323654175,
        "min": 1.96534991264,
        "stdev": 5.59185171127,
        "var": 31.2688064575
    },
    "melbands_flatness_db": {
        "dmean": 0.0583271421492,
        "dmean2": 0.087922513485,
        "dvar": 0.00321749737486,
        "dvar2": 0.00587704218924,
        "max": 0.710815131664,
        "mean": 0.463818103075,
        "median": 0.45536673069,
        "min": 0.00571483792737,
        "stdev": 0.0996279045939,
        "var": 0.00992571935058
    },
    "melbands_kurtosis": {
        "dmean": 11.9943227768,
        "dmean2": 18.9614009857,
        "dvar": 180.398376465,
        "dvar2": 432.791107178,
        "max": 124.64315033,
        "mean": 21.027967453,
        "median": 15.9971342087,
        "min": -1.21271133423,
        "stdev": 18.5931682587,
        "var": 345.705871582
    },
    "melbands_skewness": {
        "dmean": 0.976838052273,
        "dmean2": 1.50994300842,
        "dvar": 0.67394888401,
        "dvar2": 1.47484982014,
        "max": 7.99650430679,
        "mean": 2.90776801109,
        "median": 2.83841872215,
        "min": -0.981042563915,
        "stdev": 1.38927412033,
        "var": 1.93008267879
    },
    "melbands_spread": {
        "dmean": 1.92319321632,
        "dmean2": 2.88050580025,
        "dvar": 53.6762695312,
        "dvar2": 55.8620452881,
        "max": 138.755508423,
        "mean": 3.79298639297,
        "median": 2.46651220322,
        "min": 0.38169452548,
        "stdev": 7.87933540344,
        "var": 62.0839271545
    },
    "pitch_salience": {
        "dmean": 0.114088907838,
        "dmean2": 0.178298145533,
        "dvar": 0.00809987355024,
        "dvar2": 0.0199808254838,
        "max": 0.794943273067,
        "mean": 0.46636068821,
        "median": 0.473047465086,
        "min": 0.109495528042,
        "stdev": 0.132987290621,
        "var": 0.0176856182516
    },
    "silence_rate_20dB": {
        "dmean": 0.00579710165039,
        "dmean2": 0.0116279069334,
        "dvar": 0.00576350232586,
        "dvar2": 0.0173067916185,
        "max": 1,
        "mean": 0.997109830379,
        "median": 1,
        "min": 0,
        "stdev": 0.0536825358868,
        "var": 0.0028818147257
    },
    "silence_rate_30dB": {
        "dmean": 0.12753623724,
        "dmean2": 0.255813956261,
        "dvar": 0.111270926893,
        "dvar2": 0.219442650676,
        "max": 1,
        "mean": 0.82369941473,
        "median": 1,
        "min": 0,
        "stdev": 0.381075978279,
        "var": 0.145218893886
    },
    "silence_rate_60dB": {
        "dmean": 0.0231884066015,
        "dmean2": 0.0465116277337,
        "dvar": 0.0226507280022,
        "dvar2": 0.050162255764,
        "max": 1,
        "mean": 0.0751445069909,
        "median": 0,
        "min": 0,
        "stdev": 0.263624370098,
        "var": 0.0694978162646
    },
    "spectral_centroid": {
        "dmean": 95.7700271606,
        "dmean2": 132.955551147,
        "dvar": 336143.625,
        "dvar2": 329410.78125,
        "max": 11250.390625,
        "mean": 312.438934326,
        "median": 259.562011719,
        "min": 126.647407532,
        "stdev": 599.26776123,
        "var": 359121.875
    },
    "spectral_complexity": {
        "dmean": 1.58840584755,
        "dmean2": 2.61627912521,
        "dvar": 2.15522432327,
        "dvar2": 4.93996095657,
        "max": 15,
        "mean": 6.18786144257,
        "median": 6,
        "min": 0,
        "stdev": 2.49900960922,
        "var": 6.24504852295
    },
    "spectral_decrease": {
        "dmean": 1.04497015485e-08,
        "dmean2": 1.63344928694e-08,
        "dvar": 3.27830364419e-16,
        "dvar2": 7.66554864628e-16,
        "max": 5.37091125273e-29,
        "mean": -1.42510288015e-08,
        "median": -6.1473355295e-09,
        "min": -1.15057886774e-07,
        "stdev": 2.0706369952e-08,
        "var": 4.28753784219e-16
    },
    "spectral_energy": {
        "dmean": 0.0398477986455,
        "dmean2": 0.0623040795326,
        "dvar": 0.00476402277127,
        "dvar2": 0.0111511275172,
        "max": 0.438461512327,
        "mean": 0.0543940216303,
        "median": 0.0235555768013,
        "min": 1.08392301518e-20,
        "stdev": 0.0788585320115,
        "var": 0.00621866853908
    },
    "spectral_energyband_high": {
        "dmean": 4.51205960417e-06,
        "dmean2": 6.81011033521e-06,
        "dvar": 6.90104987044e-11,
        "dvar2": 1.34403252416e-10,
        "max": 7.3102004535e-05,
        "mean": 5.12416454512e-06,
        "median": 1.72201544046e-06,
        "min": 7.81669038315e-21,
        "stdev": 9.63852653513e-06,
        "var": 9.29011936823e-11
    },
    "spectral_energyband_low": {
        "dmean": 0.0363528467715,
        "dmean2": 0.0573848448694,
        "dvar": 0.0043012551032,
        "dvar2": 0.0100549599156,
        "max": 0.425311386585,
        "mean": 0.0452866069973,
        "median": 0.0158258359879,
        "min": 9.45856089828e-23,
        "stdev": 0.0741784498096,
        "var": 0.00550244189799
    },
    "spectral_energyband_middle_high": {
        "dmean": 0.000142904391396,
        "dmean2": 0.000208103985642,
        "dvar": 4.28100754846e-08,
        "dvar2": 8.72819043707e-08,
        "max": 0.00209421431646,
        "mean": 0.000283434288576,
        "median": 0.000123662219266,
        "min": 1.55837030775e-21,
        "stdev": 0.000396367686335,
        "var": 1.57107351129e-07
    },
    "spectral_energyband_middle_low": {
        "dmean": 0.0107042947784,
        "dmean2": 0.0170756820589,
        "dvar": 0.000339290767442,
        "dvar2": 0.000893310294487,
        "max": 0.135655164719,
        "mean": 0.0130125992,
        "median": 0.00698729790747,
        "min": 2.97678947126e-22,
        "stdev": 0.0185799505562,
        "var": 0.000345214590197
    },
    "spectral_entropy": {
        "dmean": 0.387240588665,
        "dmean2": 0.588354468346,
        "dvar": 0.141610905528,
        "dvar2": 0.264375865459,
        "max": 9.79306983948,
        "mean": 5.88027906418,
        "median": 5.84180831909,
        "min": 4.35049104691,
        "stdev": 0.608274102211,
        "var": 0.369997352362
    },
    "spectral_flux": {
        "dmean": 0.0632228627801,
        "dmean2": 0.103890277445,
        "dvar": 0.00769166182727,
        "dvar2": 0.0148884691298,
        "max": 0.565753638744,
        "mean": 0.129137307405,
        "median": 0.0877448692918,
        "min": 1.04111622101e-10,
        "stdev": 0.115967854857,
        "var": 0.0134485429153
    },
    "spectral_kurtosis": {
        "dmean": 14.9422273636,
        "dmean2": 23.0142192841,
        "dvar": 248.900299072,
        "dvar2": 530.788146973,
        "max": 166.212799072,
        "mean": 34.1427116394,
        "median": 26.5035171509,
        "min": -1.19570875168,
        "stdev": 24.4074020386,
        "var": 595.721313477
    },
    "spectral_rms": {
        "dmean": 0.00225076125935,
        "dmean2": 0.00339609035291,
        "dvar": 8.06838215794e-06,
        "dvar2": 1.73867138074e-05,
        "max": 0.0206825379282,
        "mean": 0.00595959555358,
        "median": 0.00479385536164,
        "min": 3.25190070184e-12,
        "stdev": 0.00418933527544,
        "var": 1.7550530174e-05
    },
    "spectral_rolloff": {
        "dmean": 137.188232422,
        "dmean2": 196.928604126,
        "dvar": 970800.8125,
        "dvar2": 974997.6875,
        "max": 18604.6875,
        "mean": 305.261322021,
        "median": 215.33203125,
        "min": 64.599609375,
        "stdev": 997.76751709,
        "var": 995540
    },
    "spectral_skewness": {
        "dmean": 0.993825018406,
        "dmean2": 1.4901714325,
        "dvar": 0.82830530405,
        "dvar2": 1.69322967529,
        "max": 10.281162262,
        "mean": 4.55096244812,
        "median": 4.18618822098,
        "min": -0.00871563795954,
        "stdev": 1.58386158943,
        "var": 2.50861740112
    },
    "spectral_spread": {
        "dmean": 821168.625,
        "dmean2": 1170614.375,
        "dvar": 5.15626447667e+12,
        "dvar2": 5.07164963635e+12,
        "max": 40776696,
        "mean": 2403499,
        "median": 2020749.375,
        "min": 543360.625,
        "stdev": 2529723.5,
        "var": 6.39950127104e+12
    },
    "spectral_strongpeak": {
        "dmean": 0.278698831797,
        "dmean2": 0.446128100157,
        "dvar": 0.113073788583,
        "dvar2": 0.271397531033,
        "max": 2.63026499748,
        "mean": 0.522365689278,
        "median": 0.411288976669,
        "min": 4.06818889687e-09,
        "stdev": 0.448095798492,
        "var": 0.20078985393
    },
    "zerocrossingrate": {
        "dmean": 0.00409731641412,
        "dmean2": 0.00381114869379,
        "dvar": 0.000247613701504,
        "dvar2": 6.9917710789e-05,
        "max": 0.5166015625,
        "mean": 0.0133204814047,
        "median": 0.00927734375,
        "min": 0.00244140625,
        "stdev": 0.0331544466317,
        "var": 0.00109921745025
    },
    "barkbands": {
        "dmean": [0.00111215224024, 0.0234234873205, 0.0152310533449, 0.00713672488928, 0.0033316470217, 0.000940706057008, 0.000255973340245, 0.000229830286116, 0.000305282417685, 6.75255869282e-05, 3.80329584004e-05, 1.61633070093e-05, 2.06089534913e-05, 1.28243209474e-05, 6.86586508891e-06, 7.36482888897e-06, 4.39154382548e-06, 2.72353827313e-06, 1.61123750786e-06, 8.95344442142e-07, 7.80273353485e-07, 9.34127399432e-07, 8.80712718754e-07, 7.64933531627e-07, 5.56856321055e-07, 4.19450486788e-07, 1.90344651152e-09],
        "dmean2": [0.00171048589982, 0.0364315211773, 0.0280571877956, 0.0125374002382, 0.00520949158818, 0.00141026766505, 0.000438517308794, 0.000368924025679, 0.000471687846584, 0.000101530677057, 5.87497270317e-05, 2.60583929048e-05, 2.83355439024e-05, 1.87889199879e-05, 1.06650795715e-05, 1.21137509268e-05, 7.1802282946e-06, 4.32970182374e-06, 2.53672715189e-06, 1.41040720791e-06, 1.21888194826e-06, 1.47142316109e-06, 1.34982610689e-06, 1.15226589514e-06, 8.42746601393e-07, 6.81535198055e-07, 3.51692452938e-09],
        "dvar": [4.53655775345e-06, 0.00169364491012, 0.00138191215228, 0.000243790549575, 5.24111346749e-05, 3.15811894325e-06, 2.03414373345e-07, 1.73233217993e-07, 6.3724831989e-07, 1.8027005666e-08, 7.50398321259e-09, 1.37905009634e-09, 2.06279016091e-09, 6.19987394757e-10, 1.07732656129e-10, 1.67498834247e-10, 1.01343690384e-10, 3.49391349186e-11, 9.78493154558e-12, 3.08038967597e-12, 3.05845713339e-12, 3.56184005901e-12, 2.64857385156e-12, 2.27284185396e-12, 9.5801209847e-13, 1.12374660358e-12, 8.86444546566e-18],
        "dvar2": [1.02157009678e-05, 0.00336778140627, 0.0039587719366, 0.000657981378026, 0.000126182640088, 6.22455308985e-06, 5.75056901653e-07, 4.20454739469e-07, 1.29673492211e-06, 3.86199374702e-08, 1.31982806906e-08, 3.31059113456e-09, 2.98813862543e-09, 1.16901222036e-09, 2.51384607575e-10, 4.17817419551e-10, 2.62472682477e-10, 7.76011616077e-11, 2.20498272419e-11, 7.26937824172e-12, 6.66622486378e-12, 6.94568881576e-12, 5.68958812355e-12, 4.71215514525e-12, 1.75992824914e-12, 2.84827109814e-12, 2.81463886766e-17],
        "max": [0.0125431949273, 0.23937523365, 0.20183429122, 0.109692849219, 0.0840228199959, 0.0171144399792, 0.00487911468372, 0.00412070564926, 0.00893000420183, 0.00175874913111, 0.0013800211018, 0.000355183088686, 0.000641370250378, 0.000353534589522, 8.29676137073e-05, 8.78442151588e-05, 0.000107504230982, 5.91883836023e-05, 1.98832403839e-05, 1.29548770929e-05, 1.48295739564e-05, 1.75257100636e-05, 1.57286704052e-05, 1.35887621582e-05, 9.09839491214e-06, 1.17804584079e-05, 2.21311946547e-08],
        "mean": [0.00110167742241, 0.0281874816865, 0.0118120573461, 0.00619655055925, 0.00432411814108, 0.00127649155911, 0.00035428578849, 0.000276442879112, 0.00056839856552, 0.000125695049064, 5.30188226548e-05, 1.93885152839e-05, 4.04120983148e-05, 2.05659962376e-05, 9.18635851122e-06, 1.15378124974e-05, 5.96103109274e-06, 3.25192877426e-06, 1.92024526768e-06, 9.91022830021e-07, 8.26801112908e-07, 1.07383550585e-06, 9.2074509439e-07, 8.30632757243e-07, 6.73345653013e-07, 3.67987155414e-07, 1.58516233473e-09],
        "median": [0.000178427129867, 0.00539415795356, 0.00381350144744, 0.00160693563521, 0.00183610990644, 0.000574015488382, 0.000200803478947, 6.97605428286e-05, 7.48027669033e-05, 1.96816108655e-05, 1.30368662212e-05, 6.3760262492e-06, 1.12423440441e-05, 5.37549567525e-06, 3.55563338417e-06, 6.15011413174e-06, 2.11705400943e-06, 9.6885264611e-07, 6.84611961788e-07, 3.65760911336e-07, 2.52443612681e-07, 3.20625645145e-07, 2.79433379546e-07, 2.53667849393e-07, 2.20229239289e-07, 5.67851543565e-08, 4.63042271193e-10],
        "min": [1.09156592499e-23, 5.54134206913e-23, 1.95037875544e-23, 2.11614383294e-23, 5.86524204592e-23, 7.69330476256e-23, 3.08891456313e-23, 4.38005077977e-23, 4.44682280668e-23, 1.20482183318e-22, 4.42773742149e-23, 2.29088378097e-23, 1.33994373504e-22, 1.30451062754e-22, 1.57018206724e-22, 2.20790328147e-22, 2.00386952015e-22, 2.10664332863e-22, 1.66233452627e-22, 2.95468596735e-22, 3.7116256476e-22, 4.0446024473e-22, 8.54196359632e-22, 8.44362482696e-22, 1.14531879978e-21, 1.72618982518e-21, 2.58233468387e-21],
        "stdev": [0.00233511161059, 0.0504128783941, 0.0286661144346, 0.0138889160007, 0.00844691880047, 0.00224670465104, 0.000465602206532, 0.000514862884302, 0.00131809304003, 0.000264235015493, 0.000138645918923, 3.91744870285e-05, 8.51301811053e-05, 3.95739734813e-05, 1.30247826746e-05, 1.52671327669e-05, 1.01154391814e-05, 6.48293234917e-06, 3.36820130542e-06, 1.80788504167e-06, 1.87550176634e-06, 2.14634383155e-06, 1.7963617438e-06, 1.66863526374e-06, 1.17745003081e-06, 9.55802306635e-07, 2.81410805769e-09],
        "var": [5.45274633623e-06, 0.00254145823419, 0.000821746129077, 0.000192901992705, 7.13504341547e-05, 5.04768149767e-06, 2.16785409179e-07, 2.65083798467e-07, 1.73736930265e-06, 6.98201390037e-08, 1.92226892182e-08, 1.53464041475e-09, 7.24714732669e-09, 1.56609947233e-09, 1.69644964743e-10, 2.33085328816e-10, 1.02322109119e-10, 4.20284120006e-11, 1.134478015e-11, 3.26844844592e-12, 3.51750703217e-12, 4.60679194444e-12, 3.22691547962e-12, 2.78434350229e-12, 1.38638861676e-12, 9.13557966255e-13, 7.91920384582e-18]
    },
    "erbbands": {
        "dmean": [0.804432570934, 5.42060613632, 15.7354984283, 24.0926933289, 11.5934028625, 15.5903282166, 6.39016342163, 8.79376888275, 5.58048200607, 3.38860106468, 6.4136505127, 7.15715646744, 2.05546402931, 2.09221816063, 1.34647798538, 0.709707975388, 1.07193171978, 0.554094433784, 0.502598285675, 0.388017743826, 0.282092452049, 0.27427688241, 0.157254055142, 0.0995213910937, 0.0639706626534, 0.0430400408804, 0.0303820427507, 0.0335897132754, 0.033471275121, 0.0322769507766, 0.0230369847268, 0.016940318048, 0.0121167236939, 0.0063922344707, 0.00386752188206, 0.00263396510854, 0.000617925776169, 1.89602997125e-05, 1.77267265826e-05, 4.31626176578e-05],
        "dmean2": [1.18257772923, 9.00217914581, 29.125541687, 42.5553016663, 18.8729743958, 24.5214214325, 9.34155750275, 13.249546051, 8.95247650146, 5.53413391113, 9.85341644287, 11.0387792587, 3.3203933239, 3.07791519165, 2.07836127281, 1.13559949398, 1.43814361095, 0.810345590115, 0.773924291134, 0.621683597565, 0.465104579926, 0.43990406394, 0.251396566629, 0.156808316708, 0.102853797376, 0.0681740939617, 0.0486759580672, 0.0532042384148, 0.0523047484457, 0.0487169995904, 0.0355828888714, 0.0254475995898, 0.0182326938957, 0.00985543057323, 0.00590450828895, 0.00418446026742, 0.00104338116944, 3.28642199747e-05, 2.77363669738e-05, 6.74991824781e-05],
        "dvar": [2.16459774971, 99.0629043579, 1409.40234375, 2852.61474609, 400.759338379, 1663.74560547, 55.7522583008, 403.134338379, 94.1418304443, 24.8804569244, 154.703674316, 443.394378662, 22.0575046539, 18.4171829224, 8.02835178375, 2.56634354591, 5.9018611908, 1.44793105125, 0.569548249245, 0.500071763992, 0.259557425976, 0.373777300119, 0.109617725015, 0.0494495779276, 0.0154696460813, 0.00699272705242, 0.00446825940162, 0.00531322788447, 0.0043337973766, 0.00349539006129, 0.00207180064172, 0.00112107209861, 0.000558433006518, 0.000137059410918, 4.99161578773e-05, 3.41858103639e-05, 3.17221906698e-06, 3.61898089274e-09, 9.27693588615e-10, 5.58413004725e-09],
        "dvar2": [4.04284715652, 223.772613525, 4017.07592773, 7852.71240234, 1032.87487793, 3994.65380859, 110.980865479, 814.901916504, 221.818450928, 67.4439086914, 357.472686768, 912.456665039, 55.5338897705, 37.8850746155, 13.4025154114, 6.02069711685, 8.41888237, 2.70303463936, 1.37454116344, 1.06904137135, 0.663488328457, 0.972141027451, 0.249584823847, 0.111651949584, 0.0334410741925, 0.016499819234, 0.00987389590591, 0.0115511463955, 0.00854842364788, 0.00730157224461, 0.00439676968381, 0.00243068183772, 0.00112509366591, 0.000240612542257, 9.85595834209e-05, 8.08036420494e-05, 8.4023895397e-06, 9.92691528978e-09, 2.17002149583e-09, 1.30833646139e-08],
        "max": [8.52913188934, 62.8592453003, 229.459457397, 360.735168457, 138.676544189, 456.6769104, 65.9053955078, 199.317138672, 94.4362487793, 43.6629257202, 121.895782471, 260.481964111, 58.979839325, 53.2398376465, 47.2923240662, 17.5239906311, 34.8495292664, 19.1061534882, 5.49686956406, 6.64977455139, 3.55823254585, 6.51275253296, 2.84843730927, 2.13037896156, 0.797684133053, 0.613420784473, 0.552318155766, 0.557498991489, 0.572790563107, 0.569498956203, 0.441006839275, 0.299309581518, 0.223735138774, 0.104967594147, 0.0636259764433, 0.0618424862623, 0.0202167630196, 0.000601595384069, 0.000194648804609, 0.000474684027722],
        "mean": [0.93264144659, 5.86211299896, 12.8738489151, 20.20170784, 12.6697244644, 19.7419433594, 8.92914485931, 11.4286766052, 7.40689277649, 4.76924991608, 9.29974079132, 13.4723176956, 2.84850311279, 4.1212143898, 2.03626346588, 1.00423502922, 2.12400197983, 0.958277881145, 0.813631534576, 0.649442911148, 0.394602030516, 0.381630063057, 0.202827051282, 0.11579503864, 0.0760520622134, 0.0478850528598, 0.0319491662085, 0.0355077572167, 0.0381345786154, 0.0355035662651, 0.0241382438689, 0.0180282052606, 0.0132717313245, 0.00808519031852, 0.00444781314582, 0.00252820900641, 0.000494750915095, 1.53660585056e-05, 2.47686130024e-05, 5.90504823776e-05],
        "median": [0.115174345672, 1.44232320786, 4.71849536896, 6.06427001953, 5.53933572769, 6.69701433182, 5.10663414001, 4.06129741669, 3.57291030884, 2.46072840691, 2.09345340729, 1.82682347298, 1.11960363388, 0.751913785934, 0.631836533546, 0.421658217907, 0.591670274734, 0.387324154377, 0.387662142515, 0.333869218826, 0.212856918573, 0.13835015893, 0.0692240893841, 0.0429737195373, 0.025528345257, 0.0179090239108, 0.0104812085629, 0.0105455936864, 0.011176943779, 0.0120774582028, 0.00705414963886, 0.00580473616719, 0.00420917384326, 0.00261709094048, 0.00146180368029, 0.000528505537659, 6.11215218669e-05, 3.31034334522e-06, 1.12889647426e-05, 2.57000410784e-05],
        "min": [1.50379385586e-21, 1.25344116093e-20, 2.27549453981e-20, 5.54257991684e-20, 4.74607833461e-20, 2.15755315705e-19, 6.32258189542e-19, 6.82811022485e-19, 4.33346429533e-19, 8.81595448379e-19, 5.39227098903e-19, 1.23491199855e-18, 1.78049551517e-18, 4.65490058091e-18, 1.50179313779e-18, 1.2164825179e-18, 6.26119434062e-18, 5.56894425677e-18, 7.63362387524e-18, 9.23165492781e-18, 1.45868801161e-17, 1.00990514074e-17, 1.1260951482e-17, 8.03540286955e-18, 1.04320958287e-17, 1.48181647785e-17, 1.39756747071e-17, 1.5194503833e-17, 1.37211810112e-17, 2.19630580878e-17, 2.35496467509e-17, 1.71674817952e-17, 1.45128573775e-17, 1.05239807055e-17, 9.73563043244e-18, 6.42617427302e-18, 3.24906804559e-18, 1.36325031136e-18, 4.15624782842e-19, 3.2473705288e-20],
        "stdev": [1.83490157127, 10.7186040878, 29.15483284, 44.8891372681, 20.770067215, 47.4300956726, 10.3484783173, 24.3030719757, 11.1024284363, 6.37804794312, 17.9819889069, 32.8230133057, 5.05561494827, 8.81053161621, 4.75065755844, 1.76951563358, 4.57085895538, 1.9585365057, 0.986194729805, 0.969797432423, 0.539144933224, 0.63238042593, 0.364709705114, 0.22791646421, 0.134836658835, 0.0859120637178, 0.0699773877859, 0.0785838961601, 0.0754382014275, 0.0667776912451, 0.0499635152519, 0.0362480282784, 0.0267531443387, 0.0145063186064, 0.0079677645117, 0.00569482613355, 0.00150084635243, 4.87639372295e-05, 3.4906235669e-05, 8.5306710389e-05],
        "var": [3.36686396599, 114.88848114, 850.004272461, 2015.0345459, 431.395690918, 2249.61401367, 107.091003418, 590.639343262, 123.263908386, 40.6794967651, 323.351928711, 1077.35021973, 25.5592403412, 77.6254653931, 22.5687465668, 3.13118577003, 20.8927536011, 3.83586525917, 0.972580015659, 0.940507113934, 0.290677249432, 0.399905025959, 0.133013173938, 0.051945913583, 0.0181809253991, 0.00738088227808, 0.00489683495834, 0.00617542909458, 0.00569092249498, 0.00445925956592, 0.00249635288492, 0.00131391966715, 0.000715730770025, 0.000210433267057, 6.3485269493e-05, 3.24310422002e-05, 2.25253984354e-06, 2.37792141533e-09, 1.21844534462e-09, 7.27723525884e-09]
    },
    "gfcc": {
        "mean": [-160.155700684, 186.186828613, -51.6439208984, 22.2906169891, -38.3705673218, 15.2069787979, -33.2414855957, 1.04078912735, -8.83444881439, -7.58781433105, -8.9057302475, -11.47290802, -2.25222277641],
        "cov": [[12100.4863281, 704.998718262, -734.105957031, 147.618026733, -210.93800354, 139.833190918, -173.396087646, 73.464630127, -108.366676331, -94.3237457275, 19.2164516449, 86.0264663696, -26.7951335907], [704.998718262, 692.978149414, 88.7664413452, -145.578430176, 222.640869141, -99.1544723511, 62.5243034363, -82.0455322266, 107.73236084, -108.978385925, 63.9871940613, -113.609977722, 57.4744606018], [-734.105957031, 88.7664413452, 1033.79541016, 101.587623596, 70.1915435791, 6.63059949875, 120.976158142, -67.8234176636, 55.5743370056, 79.7911148071, 63.0838317871, 0.80721026659, 42.0836677551], [147.618026733, -145.578430176, 101.587623596, 205.155654907, -29.4667549133, 17.0566978455, 18.5075187683, -6.0725312233, -7.69541311264, 33.3628387451, 14.077624321, 9.19340515137, 7.64030790329], [-210.93800354, 222.640869141, 70.1915435791, -29.4667549133, 313.648406982, 15.5531787872, 103.79032135, -18.8354167938, 94.1768569946, -40.3065643311, 46.6431427002, -20.1493110657, 54.7585601807], [139.833190918, -99.1544723511, 6.63059949875, 17.0566978455, 15.5531787872, 141.838775635, 10.6348838806, -16.9988937378, -32.3734855652, 28.8571586609, 15.0986766815, 57.7589035034, 13.9435386658], [-173.396087646, 62.5243034363, 120.976158142, 18.5075187683, 103.79032135, 10.6348838806, 132.395080566, 26.7769184113, 57.0251808167, -9.28742408752, 31.4792118073, -13.5578403473, 9.11868286133], [73.464630127, -82.0455322266, -67.8234176636, -6.0725312233, -18.8354167938, -16.9988937378, 26.7769184113, 127.620117188, 43.6527862549, 13.2527713776, -40.6182136536, -21.9804611206, -33.1394996643], [-108.366676331, 107.73236084, 55.5743370056, -7.69541311264, 94.1768569946, -32.3734855652, 57.0251808167, 43.6527862549, 124.7866745, 19.9483547211, 15.0812654495, -49.6898727417, 11.1398048401], [-94.3237457275, -108.978385925, 79.7911148071, 33.3628387451, -40.3065643311, 28.8571586609, -9.28742408752, 13.2527713776, 19.9483547211, 102.75881958, 21.6644744873, 28.4949169159, 1.04849326611], [19.2164516449, 63.9871940613, 63.0838317871, 14.077624321, 46.6431427002, 15.0986766815, 31.4792118073, -40.6182136536, 15.0812654495, 21.6644744873, 80.1664581299, 31.3637123108, 32.6522979736], [86.0264663696, -113.609977722, 0.80721026659, 9.19340515137, -20.1493110657, 57.7589035034, -13.5578403473, -21.9804611206, -49.6898727417, 28.4949169159, 31.3637123108, 114.913833618, 29.0341396332], [-26.7951335907, 57.4744606018, 42.0836677551, 7.64030790329, 54.7585601807, 13.9435386658, 9.11868286133, -33.1394996643, 11.1398048401, 1.04849326611, 32.6522979736, 29.0341396332, 67.0749511719]],
        "icov": [[0.000180869406904, -0.000899532635231, 0.000142541946843, -0.000782519578934, 0.000262596848188, -0.000531237397809, 0.00035287369974, -0.000723190314602, 0.000183719646884, -0.000127244202304, 0.000247901887633, -0.000842095643748, 0.000548823969439], [-0.000899532635231, 0.00961587950587, -0.00117569603026, 0.0070150368847, -0.00203368184157, 0.00366084114648, -0.00104760646354, 0.00567195517942, -0.00327131175436, 0.00488819880411, -0.00597982946783, 0.00871376413852, -0.00521029112861], [0.000142541946843, -0.00117569603026, 0.00158542697318, -0.00116584519856, 0.000394805538235, 6.07349866186e-05, -0.00188000628259, 0.000929653295316, 0.000377277610824, -0.00228541367687, 0.00169206352439, -0.000961582700256, 0.000147994898725], [-0.000782519578934, 0.0070150368847, -0.00116584519856, 0.0109748523682, -0.000746046367567, 0.00273373979144, -0.00283929309808, 0.00445639900863, -0.000741592375562, 0.00113529257942, -0.00404343055561, 0.00752952601761, -0.00539916427806], [0.000262596848188, -0.00203368184157, 0.000394805538235, -0.000746046367567, 0.00781246228144, -0.00294710393064, -0.00285108131357, 0.000925234169699, -0.00520365731791, 0.00301545974799, 0.000748468039092, -0.00219786167145, -0.00183168437798], [-0.000531237397809, 0.00366084114648, 6.07349866186e-05, 0.00273373979144, -0.00294710393064, 0.0125963529572, -0.00411676755175, 0.00400426704437, 0.00310284504667, -0.00388800282963, 0.00114579580259, -0.000195555199753, -0.00230078864843], [0.00035287369974, -0.00104760646354, -0.00188000628259, -0.00283929309808, -0.00285108131357, -0.00411676755175, 0.0186419039965, -0.00848021451384, -0.00323509983718, 0.00711265346035, -0.00923180300742, -0.00061362789711, 0.00418661208823], [-0.000723190314602, 0.00567195517942, 0.000929653295316, 0.00445639900863, 0.000925234169699, 0.00400426704437, -0.00848021451384, 0.0217042267323, -0.00983317475766, -0.00119217275642, 0.00863295979798, 0.000444137491286, 0.00130546395667], [0.000183719646884, -0.00327131175436, 0.000377277610824, -0.000741592375562, -0.00520365731791, 0.00310284504667, -0.00323509983718, -0.00983317475766, 0.0262022968382, -0.0121999802068, -0.00162275112234, 0.00799210648984, -0.00492154387757], [-0.000127244202304, 0.00488819880411, -0.00228541367687, 0.00113529257942, 0.00301545974799, -0.00388800282963, 0.00711265346035, -0.00119217275642, -0.0121999802068, 0.0241473689675, -0.0111878141761, -0.000564240326639, 0.00119492958765], [0.000247901887633, -0.00597982946783, 0.00169206352439, -0.00404343055561, 0.000748468039092, 0.00114579580259, -0.00923180300742, 0.00863295979798, -0.00162275112234, -0.0111878141761, 0.0323146246374, -0.0122400652617, -0.000695226655807], [-0.000842095643748, 0.00871376413852, -0.000961582700256, 0.00752952601761, -0.00219786167145, -0.000195555199753, -0.00061362789711, 0.000444137491286, 0.00799210648984, -0.000564240326639, -0.0122400652617, 0.0273256022483, -0.0131077161059], [0.000548823969439, -0.00521029112861, 0.000147994898725, -0.00539916427806, -0.00183168437798, -0.00230078864843, 0.00418661208823, 0.00130546395667, -0.00492154387757, 0.00119492958765, -0.000695226655807, -0.0131077161059, 0.0289750397205]]
    },
    "melbands": {
        "dmean": [0.00683558173478, 0.00742538645864, 0.00362234772183, 0.000894633471034, 0.000304574758047, 0.000188276710105, 7.94769730419e-05, 3.75170675397e-05, 6.12356670899e-05, 3.96835057472e-05, 9.36274500418e-06, 8.74238230608e-06, 5.47267836737e-06, 1.71677913841e-06, 2.49426057053e-06, 1.85396095276e-06, 1.01163789168e-06, 9.19000001431e-07, 4.73513296129e-07, 5.93369975377e-07, 2.79457481156e-07, 2.79598907582e-07, 2.42927825411e-07, 1.00015775217e-07, 8.06025965971e-08, 5.7489309313e-08, 3.72900323953e-08, 2.65697259749e-08, 1.85563564514e-08, 1.79943810963e-08, 2.06126475888e-08, 2.00339709266e-08, 1.70691230039e-08, 1.91017779372e-08, 1.42449794183e-08, 1.10742490733e-08, 1.01767794192e-08, 8.84064998985e-09, 7.1418182479e-09, 4.99500973916e-09],
        "dmean2": [0.0102374078706, 0.0130126653239, 0.00636211642995, 0.00139949237928, 0.000453620508779, 0.000283181318082, 0.000127345105284, 6.21206054348e-05, 9.35404168558e-05, 6.16460529272e-05, 1.52928223542e-05, 1.28687470351e-05, 8.35915761854e-06, 2.86706676889e-06, 3.63931917491e-06, 2.50899984167e-06, 1.45298031384e-06, 1.42135377246e-06, 7.57933719342e-07, 9.77326749307e-07, 4.62210067553e-07, 4.52764282954e-07, 3.9894831616e-07, 1.61732003789e-07, 1.27746545786e-07, 8.90967228884e-08, 5.93689968298e-08, 4.24979162972e-08, 3.01375600031e-08, 2.84836314535e-08, 3.33592140578e-08, 3.18774517893e-08, 2.58322323532e-08, 2.93041999555e-08, 2.22615170742e-08, 1.63133595521e-08, 1.55725015105e-08, 1.32987754142e-08, 1.06694271196e-08, 7.79268294337e-09],
        "dvar": [0.000141349708429, 0.000247450661846, 6.2481740315e-05, 3.58877628059e-06, 2.52453389749e-07, 1.6477930842e-07, 1.83383850327e-08, 3.3597000737e-09, 1.47438701248e-08, 1.33768836008e-08, 5.41154843159e-10, 3.37069067102e-10, 1.61008872901e-10, 1.94634742351e-11, 2.00692171215e-11, 1.39405960733e-11, 4.84415068822e-12, 2.11729288616e-12, 4.99071649892e-13, 1.15090565116e-12, 2.84865501413e-13, 4.68260142033e-13, 2.70746641252e-13, 7.2054036728e-14, 3.14786852184e-14, 1.24642117916e-14, 5.38113128072e-15, 2.66716254354e-15, 1.62373791357e-15, 1.61002402664e-15, 2.02949941195e-15, 1.67645840888e-15, 1.28557642064e-15, 1.16495374087e-15, 8.15857899631e-16, 5.37222282346e-16, 3.92462287017e-16, 3.35817832172e-16, 1.56090291843e-16, 8.95820655353e-17],
        "dvar2": [0.000270980090136, 0.000668963475619, 0.000171968931681, 8.81891901372e-06, 5.42013253835e-07, 3.29711809854e-07, 4.15937186915e-08, 8.93795792933e-09, 3.27680851342e-08, 2.7522013113e-08, 1.37048006277e-09, 6.87535861577e-10, 2.60388960394e-10, 5.10073962234e-11, 3.48250837889e-11, 2.0962082764e-11, 9.07313026793e-12, 4.90499134365e-12, 1.14094215846e-12, 2.79360996142e-12, 7.08604344906e-13, 1.21110098946e-12, 6.83379459791e-13, 1.56720258515e-13, 7.19200496683e-14, 2.82961537366e-14, 1.19160069859e-14, 6.48754011599e-15, 3.58964389178e-15, 3.50394469807e-15, 4.5189618547e-15, 3.52116551316e-15, 2.51105437137e-15, 2.6397351932e-15, 1.84549484493e-15, 1.11743720424e-15, 8.68345937334e-16, 7.22717362657e-16, 2.95883881539e-16, 1.61388138821e-16],
        "max": [0.0727420672774, 0.106695361435, 0.052781265229, 0.0215323399752, 0.00536920782179, 0.00398515956476, 0.00121748493984, 0.000507415097672, 0.00127444416285, 0.00143243896309, 0.000297009130009, 0.000228665594477, 0.00021681029466, 4.70449049317e-05, 5.04577037646e-05, 5.12807200721e-05, 3.40653641615e-05, 1.09314150905e-05, 5.00370651935e-06, 8.17082673166e-06, 3.93032451029e-06, 7.24611527403e-06, 4.62133675683e-06, 3.29048998537e-06, 1.59529599841e-06, 7.92055061538e-07, 5.25221139469e-07, 3.91952625023e-07, 3.69806741674e-07, 3.56761859166e-07, 3.41124973602e-07, 3.54268024694e-07, 4.19379318828e-07, 2.96177773862e-07, 2.62245521299e-07, 2.21193758421e-07, 1.67734000911e-07, 1.73404743009e-07, 1.12394417329e-07, 8.1192034429e-08],
        "mean": [0.00807101838291, 0.00701208040118, 0.00315451342613, 0.00112884968985, 0.000419620395405, 0.000247902033152, 0.000106918741949, 4.97212604387e-05, 9.43282284425e-05, 7.37786540412e-05, 1.17084946396e-05, 1.7559457774e-05, 8.06746174931e-06, 1.83988322533e-06, 4.68700091005e-06, 3.29630279339e-06, 1.65492099313e-06, 1.44887167153e-06, 6.93271601904e-07, 9.42740712162e-07, 3.40645812003e-07, 3.54793940005e-07, 3.47332843376e-07, 1.04081365748e-07, 9.27149272911e-08, 6.38241814954e-08, 4.33323954496e-08, 2.85979986359e-08, 1.88388771249e-08, 1.92209448358e-08, 2.1150574625e-08, 2.2148375578e-08, 1.99577208093e-08, 1.97735374741e-08, 1.42937315317e-08, 1.18979581742e-08, 1.04181117067e-08, 9.25400467366e-09, 8.35143154632e-09, 6.2573235482e-09],
        "median": [0.00124920462258, 0.00278711179271, 0.00105312059168, 0.000485521450173, 0.000217969456571, 9.55703872023e-05, 5.37923187949e-05, 2.22642047447e-05, 1.66660247487e-05, 1.02252433862e-05, 3.31599039782e-06, 2.61444347416e-06, 1.98276529773e-06, 7.44396857044e-07, 1.08801805254e-06, 9.91287151919e-07, 4.66811002298e-07, 6.17683213022e-07, 3.0951861163e-07, 4.09705648963e-07, 1.32017234478e-07, 1.17375059006e-07, 1.13918403599e-07, 3.16752313267e-08, 3.33990257673e-08, 1.69699774233e-08, 1.47783545401e-08, 1.12863247637e-08, 5.8593978558e-09, 5.51830670048e-09, 5.69365266045e-09, 6.7772258916e-09, 6.46596109988e-09, 6.0995319906e-09, 3.73068331783e-09, 4.00346911178e-09, 3.12608161579e-09, 2.76428369084e-09, 2.76613443262e-09, 2.01198657734e-09],
        "min": [1.53853451389e-23, 1.42015899308e-23, 8.97507325595e-24, 7.80339393065e-24, 2.04582524517e-23, 1.43098027144e-23, 6.4671179886e-24, 1.07933132344e-23, 4.01984150765e-24, 7.8079551244e-24, 8.45877010437e-24, 1.92404184525e-23, 5.46403953799e-24, 2.34104058284e-24, 8.14613348358e-24, 1.43320123043e-23, 1.00173241725e-23, 1.21719107751e-23, 1.19186982575e-23, 1.4692237748e-23, 1.76596058851e-23, 1.18517807646e-23, 7.74626620161e-24, 1.1233506297e-23, 5.81236619828e-24, 5.83340985179e-24, 9.45924452514e-24, 9.53705855369e-24, 8.47869673084e-24, 9.37600076698e-24, 8.32240997488e-24, 5.91255113882e-24, 1.10569402937e-23, 1.30674169973e-23, 1.34025732303e-23, 1.27764219865e-23, 9.62586930326e-24, 1.13161378991e-23, 7.61115641665e-24, 9.29516382344e-24],
        "stdev": [0.0149625465274, 0.0136209102347, 0.00669085187837, 0.00215823715553, 0.000659737095702, 0.000497888715472, 0.000159427698236, 7.32804837753e-05, 0.000190600272617, 0.000179583192221, 2.51457058766e-05, 3.85403182008e-05, 2.13997209357e-05, 4.01453098675e-06, 8.20924924483e-06, 6.6868688009e-06, 3.66308449884e-06, 1.86921784007e-06, 8.85844883669e-07, 1.33967182592e-06, 5.60515331927e-07, 6.76122795085e-07, 6.25063364623e-07, 2.71263616014e-07, 1.81390049647e-07, 1.20505191603e-07, 7.91188412563e-08, 5.17972651437e-08, 4.19165040455e-08, 4.3160351737e-08, 4.74725823096e-08, 4.49367938415e-08, 4.09702067827e-08, 3.68605270751e-08, 3.01943394732e-08, 2.56605279247e-08, 2.11576267617e-08, 1.98490255343e-08, 1.51198733533e-08, 1.15120633026e-08],
        "var": [0.000223877796088, 0.000185529192095, 4.47675010946e-05, 4.65798711957e-06, 4.35253070918e-07, 2.47893183314e-07, 2.54171919067e-08, 5.3700297542e-09, 3.63284620164e-08, 3.22501207961e-08, 6.32306484949e-10, 1.48535617139e-09, 4.57948068355e-10, 1.61164605966e-11, 6.73917727179e-11, 4.47142115001e-11, 1.3418187568e-11, 3.49397550822e-12, 7.84721137896e-13, 1.79472073054e-12, 3.14177449248e-13, 4.57142028225e-13, 3.90704179079e-13, 7.35839476374e-14, 3.29023510911e-14, 1.45215023545e-14, 6.25979159119e-15, 2.6829567434e-15, 1.75699334859e-15, 1.86281582167e-15, 2.25364614089e-15, 2.01931532307e-15, 1.67855778004e-15, 1.35869855152e-15, 9.11698195305e-16, 6.58462713828e-16, 4.47645160042e-16, 3.93983796418e-16, 2.28610592574e-16, 1.32527595491e-16]
    },
    "melbands128": {
        "dmean": [0.00106041878462, 0.00672014756128, 0.0112838847563, 0.00886380672455, 0.00824267230928, 0.00746228452772, 0.00557468924671, 0.00272479141131, 0.000792237231508, 0.00101976084989, 0.00107351201586, 0.000397002062527, 0.000216711559915, 0.000173885011463, 0.000223927097977, 0.000245965115028, 0.000117998999485, 6.71336310916e-05, 3.56841592293e-05, 4.28556413681e-05, 4.40803232777e-05, 4.02198784286e-05, 7.37811496947e-05, 8.87887435965e-05, 6.96784700267e-05, 1.6965697796e-05, 1.25827618831e-05, 9.19708418223e-06, 9.08788933884e-06, 1.25873539218e-05, 8.81187133928e-06, 6.08016853221e-06, 8.77582078829e-06, 2.87449711323e-06, 1.59426383561e-06, 1.77614754193e-06, 2.09148061003e-06, 2.86525732918e-06, 3.61764773515e-06, 3.44961972587e-06, 8.94699553555e-07, 1.44077932873e-06, 1.05901699499e-06, 1.13517512546e-06, 1.58737270795e-06, 8.38873120301e-07, 9.44632915889e-07, 3.68138699969e-07, 3.62372077234e-07, 9.21070409277e-07, 6.47220190331e-07, 5.88593650264e-07, 3.33805360242e-07, 1.90114704424e-07, 1.86056695384e-07, 3.37533037964e-07, 3.89525325772e-07, 3.31558737798e-07, 2.41926130684e-07, 9.61335189231e-08, 1.15751561225e-07, 1.00653032575e-07, 9.32483743554e-08, 8.03387010251e-08, 7.54746025677e-08, 6.72557831649e-08, 5.07456405785e-08, 4.29538999924e-08, 4.16405612214e-08, 3.71559885082e-08, 3.04756682112e-08, 2.32502017639e-08, 1.79276398171e-08, 1.95289739935e-08, 2.02711127884e-08, 2.13523989601e-08, 1.61260640397e-08, 2.15379962754e-08, 2.19355378306e-08, 2.28424816839e-08, 2.58180286039e-08, 1.85735000713e-08, 1.87350313041e-08, 1.82100485802e-08, 1.82109776148e-08, 1.96477554226e-08, 2.12510702369e-08, 1.89776212522e-08, 1.46632066489e-08, 1.30664483677e-08, 1.01658272911e-08, 1.22274919079e-08, 1.14721938616e-08, 1.16670966221e-08, 8.87208884137e-09, 9.50080369932e-09, 9.14591780088e-09, 9.79953540536e-09, 8.09304268046e-09, 6.39633723765e-09, 6.34118535459e-09, 5.3115498666e-09, 5.31586152874e-09, 4.48453407742e-09, 4.42445946547e-09, 4.84087703256e-09, 4.8902104588e-09, 4.40494796194e-09, 4.18714929395e-09, 6.2133680423e-09, 5.37236122256e-09, 2.806423538e-09, 1.47290890595e-09, 6.42216557711e-10, 9.43923619823e-11, 1.58670715456e-11, 9.14431377841e-12, 8.8809567339e-12, 8.63590882832e-12, 8.44320793836e-12, 8.24111699022e-12, 8.05391864311e-12, 7.9005699552e-12, 7.76425018029e-12, 7.65172907674e-12, 7.55995439861e-12, 7.49119689891e-12, 7.45124188045e-12],
        "dmean2": [0.00162337929942, 0.00973939616233, 0.0180180426687, 0.0149669023231, 0.0153885520995, 0.0136056337506, 0.00984517298639, 0.00478226458654, 0.00132338062394, 0.00160931749269, 0.00169701909181, 0.000654097879305, 0.000345635402482, 0.000287983857561, 0.000353329000063, 0.000369692686945, 0.000188682315638, 0.000113958631118, 5.68739633309e-05, 7.14721099939e-05, 7.52533014747e-05, 6.15387398284e-05, 0.00011390302825, 0.000132878805744, 0.00010523601668, 2.91584638035e-05, 2.23671067943e-05, 1.50005489559e-05, 1.44613113662e-05, 1.88118519873e-05, 1.34457759486e-05, 9.63393267739e-06, 1.29667660076e-05, 4.76969398733e-06, 2.77390154224e-06, 3.14108820021e-06, 3.38826566804e-06, 4.15743534177e-06, 4.90615229864e-06, 4.59193415736e-06, 1.47148386986e-06, 2.18605305236e-06, 1.57998977102e-06, 1.61519506037e-06, 2.41976954385e-06, 1.34110757699e-06, 1.42182886975e-06, 6.42694999442e-07, 6.35978494756e-07, 1.43589045365e-06, 1.09732377496e-06, 9.65727053881e-07, 5.63282242183e-07, 3.24502138938e-07, 3.32144907134e-07, 5.65314394407e-07, 6.05475349857e-07, 5.51187724795e-07, 4.02723799198e-07, 1.57529044031e-07, 1.9072217583e-07, 1.60466044008e-07, 1.50942526034e-07, 1.34005730956e-07, 1.19909614682e-07, 1.09287761063e-07, 8.2039100846e-08, 7.07447966874e-08, 6.68611264132e-08, 6.14011170796e-08, 4.82552522385e-08, 3.86949317033e-08, 2.89928241415e-08, 3.29557074963e-08, 3.2571865205e-08, 3.45105704014e-08, 2.4584378977e-08, 3.48241329107e-08, 3.53555975607e-08, 3.81227067692e-08, 4.14966301321e-08, 2.86655623682e-08, 2.92858555184e-08, 2.84855374844e-08, 2.89358244032e-08, 3.03237044363e-08, 3.47413084967e-08, 2.9779400279e-08, 2.29987708877e-08, 2.06595007768e-08, 1.57199107065e-08, 1.89568787334e-08, 1.80284676077e-08, 1.93776514834e-08, 1.4275324034e-08, 1.47756722413e-08, 1.4318538355e-08, 1.50997436776e-08, 1.31539401593e-08, 1.01176702572e-08, 1.03319424127e-08, 8.55233928121e-09, 8.37295921485e-09, 7.10567871209e-09, 7.22225035332e-09, 7.6868387211e-09, 7.82860620774e-09, 6.94636614895e-09, 6.62123378348e-09, 1.03616510927e-08, 9.06180375182e-09, 4.68601335513e-09, 2.67054245384e-09, 1.21338372683e-09, 1.82595730203e-10, 3.0103287918e-11, 1.68686453694e-11, 1.63994633845e-11, 1.59533601607e-11, 1.55852570433e-11, 1.52226842243e-11, 1.48705076031e-11, 1.46019758784e-11, 1.43619196397e-11, 1.41364177308e-11, 1.39714932332e-11, 1.38423326621e-11, 1.37683094092e-11],
        "dvar": [4.16054808738e-06, 0.000162912503583, 0.000421786826337, 0.000297389895422, 0.00038166862214, 0.000321751314914, 0.000154422523337, 3.63974249922e-05, 1.88701051229e-06, 5.85872430747e-06, 9.37970708037e-06, 3.98796714762e-07, 7.2726109579e-08, 7.13315913003e-08, 2.37185446395e-07, 5.22094126154e-07, 5.75676466497e-08, 1.52140344767e-08, 3.59824681162e-09, 5.22435739114e-09, 6.88756252032e-09, 8.80027517525e-09, 2.6436474343e-08, 5.14454221445e-08, 6.43720881044e-08, 1.49315093623e-09, 1.23454324541e-09, 7.03979874395e-10, 4.21064239031e-10, 9.37677824275e-10, 4.61196414392e-10, 2.26673638193e-10, 5.54096435401e-10, 3.58914321874e-11, 1.19475870169e-11, 4.6798547676e-11, 3.62834866319e-11, 4.174624188e-11, 8.00528532352e-11, 8.33898505803e-11, 3.32874830131e-12, 2.34209422689e-11, 9.97210647391e-12, 9.80426590608e-12, 1.05839512501e-11, 2.28454776798e-12, 3.2836008218e-12, 5.3666988388e-13, 4.56651535162e-13, 5.44795111801e-12, 1.86785070917e-12, 1.26032799648e-12, 5.48484814424e-13, 2.06658420845e-13, 2.81000049618e-13, 1.01706078455e-12, 6.31453277253e-13, 6.55643074554e-13, 3.14644062758e-13, 4.86303028012e-14, 1.24856031005e-13, 8.64881422231e-14, 5.70228746491e-14, 2.94408425319e-14, 2.81350091065e-14, 2.35256929768e-14, 9.10468769333e-15, 8.27714158607e-15, 7.41983836433e-15, 7.25327441745e-15, 3.38536283831e-15, 2.30232279503e-15, 1.38471220388e-15, 2.28428332259e-15, 2.49399766891e-15, 2.83049950665e-15, 9.98766617777e-16, 2.77845504952e-15, 2.62325299083e-15, 2.1621077138e-15, 4.12442364875e-15, 1.26472839871e-15, 1.41840982149e-15, 1.86993936875e-15, 1.7098725881e-15, 1.18301322446e-15, 1.67391106317e-15, 1.33723293669e-15, 1.05209655329e-15, 9.42888171884e-16, 5.14553721913e-16, 8.71751327419e-16, 5.52946231402e-16, 6.54817772237e-16, 2.52816147228e-16, 6.29010848856e-16, 3.39758917657e-16, 4.16845639181e-16, 2.1602220067e-16, 1.33225947686e-16, 2.25254515688e-16, 1.07621915166e-16, 1.18241471628e-16, 7.43560262686e-17, 8.75643139409e-17, 8.19173239526e-17, 7.87499170382e-17, 8.17382426587e-17, 7.63780262625e-17, 3.44589308327e-16, 2.45644610432e-16, 3.82431405218e-17, 3.86179095876e-17, 9.21637690189e-18, 2.28089005153e-19, 3.79457271833e-21, 2.05054105566e-22, 1.93376263109e-22, 1.82590716999e-22, 1.73404728369e-22, 1.65393120125e-22, 1.58259633975e-22, 1.52388981605e-22, 1.47232481858e-22, 1.43063749559e-22, 1.39736435235e-22, 1.37354857852e-22, 1.35895237985e-22],
        "dvar2": [9.14352312975e-06, 0.000314904929837, 0.000933670438826, 0.000741241616197, 0.00108939339407, 0.000913049967494, 0.0004239808477, 9.69574393821e-05, 4.62239950139e-06, 1.46746915561e-05, 2.23820570682e-05, 8.69723123742e-07, 1.56479572411e-07, 1.69938189742e-07, 5.28600537564e-07, 9.83895006357e-07, 1.45481280356e-07, 4.06196960512e-08, 9.78671632623e-09, 1.3358495643e-08, 1.77330150564e-08, 1.97791703016e-08, 5.98123719442e-08, 1.00474650822e-07, 1.28570519564e-07, 3.85258802638e-09, 3.42895201122e-09, 1.70686720313e-09, 8.57402815413e-10, 1.75672376646e-09, 9.99973437388e-10, 4.85155915442e-10, 7.76356701149e-10, 8.84652420763e-11, 3.17116263804e-11, 1.33588431983e-10, 8.00866525874e-11, 7.02394462038e-11, 1.07703131136e-10, 1.21634716188e-10, 7.78104403826e-12, 3.89468284012e-11, 1.80498671565e-11, 1.41245687021e-11, 2.2225353502e-11, 5.85503086986e-12, 6.94509120353e-12, 1.45255498168e-12, 1.16570587818e-12, 1.00579787554e-11, 5.32213943055e-12, 3.33061508061e-12, 1.39293633052e-12, 4.82459016314e-13, 7.38150100939e-13, 2.70181012979e-12, 1.40839282511e-12, 1.64583234194e-12, 7.77398924314e-13, 1.08326067842e-13, 2.8587958281e-13, 1.99801926306e-13, 1.38149975942e-13, 6.92033778373e-14, 6.62438447195e-14, 5.81118066536e-14, 2.17458429735e-14, 1.94755219303e-14, 1.72843781388e-14, 1.86327021249e-14, 8.39394150026e-15, 5.72869727458e-15, 3.30387445714e-15, 5.00261343242e-15, 6.06972883277e-15, 7.00319217493e-15, 2.04250348527e-15, 6.42453060559e-15, 5.97493271697e-15, 5.27618474559e-15, 1.01880640087e-14, 2.57775842772e-15, 2.93062049508e-15, 3.82191303142e-15, 3.55617169081e-15, 2.75855316339e-15, 4.1685976875e-15, 3.26193573834e-15, 2.58866037703e-15, 2.25301234849e-15, 1.04207795347e-15, 1.93321802387e-15, 1.31794144368e-15, 1.58772821364e-15, 5.10805230545e-16, 1.58922481498e-15, 7.37738803762e-16, 9.08535691917e-16, 4.8352997555e-16, 2.81590756419e-16, 5.43551947802e-16, 2.056948044e-16, 2.88941546564e-16, 1.64937378923e-16, 1.84486846406e-16, 1.73451939398e-16, 1.65222339336e-16, 1.80246718586e-16, 1.66913784722e-16, 9.3923163653e-16, 6.6245096846e-16, 9.58959417683e-17, 1.08115205978e-16, 2.68496225933e-17, 6.75139129099e-19, 1.14403933555e-20, 6.51650453091e-22, 6.14166711127e-22, 5.79493535417e-22, 5.51168758863e-22, 5.2514993002e-22, 5.02128974566e-22, 4.84097103642e-22, 4.67399101845e-22, 4.54424775957e-22, 4.43937091103e-22, 4.36365843948e-22, 4.31744860848e-22],
        "max": [0.0115576758981, 0.0779725909233, 0.121200114489, 0.124354742467, 0.134655073285, 0.0999489203095, 0.0856452211738, 0.0389241278172, 0.0109216691926, 0.0288475714624, 0.0329103544354, 0.0056783221662, 0.00180235691369, 0.00189079507254, 0.00495937652886, 0.00746924802661, 0.00277839833871, 0.0010196256917, 0.000473904248793, 0.000645246473141, 0.000657232594676, 0.000975232804194, 0.00150280131493, 0.0027815583162, 0.00324023514986, 0.000316560675856, 0.000293585035251, 0.000349744252162, 0.000283965986455, 0.000383069331292, 0.000266213639406, 0.000181797629921, 0.000437359442003, 5.97556499997e-05, 3.16008517984e-05, 8.58174171299e-05, 8.62106244313e-05, 8.89950897545e-05, 0.000117398303701, 0.000131879802211, 1.78126192623e-05, 7.67034071032e-05, 4.94962696393e-05, 4.49664112239e-05, 3.08531452902e-05, 1.17586350825e-05, 1.49048746607e-05, 6.80216771798e-06, 5.34943910679e-06, 2.48006563197e-05, 1.19024589367e-05, 1.01421101135e-05, 6.30195745543e-06, 4.60931960333e-06, 4.5096167014e-06, 1.14235208457e-05, 5.99778422838e-06, 7.5010607361e-06, 5.02295415572e-06, 2.00438535103e-06, 4.67252539238e-06, 3.51143444277e-06, 2.18192280954e-06, 1.1537622413e-06, 1.28076521833e-06, 1.3039998521e-06, 7.77171749178e-07, 6.95813355378e-07, 6.46857415632e-07, 6.44231533897e-07, 3.97865846935e-07, 3.51726498593e-07, 3.1142931789e-07, 5.01548072407e-07, 5.06271987888e-07, 4.9465114671e-07, 3.00882447846e-07, 4.19821844844e-07, 4.26813045351e-07, 3.96776187017e-07, 6.78411936406e-07, 3.49444007952e-07, 3.92920611603e-07, 5.40310225006e-07, 3.62891285022e-07, 3.0275316476e-07, 3.49585434378e-07, 3.06736893663e-07, 2.90787397716e-07, 3.36997317163e-07, 2.5017143912e-07, 3.26238364323e-07, 2.28202011954e-07, 2.35923494074e-07, 1.37156391133e-07, 2.38638705241e-07, 1.62707266327e-07, 1.97520606093e-07, 1.17600379212e-07, 1.10930152175e-07, 1.82165024398e-07, 8.33635738218e-08, 1.21543237697e-07, 8.32537239148e-08, 1.01102891392e-07, 6.06094303635e-08, 6.92589097184e-08, 7.54901776645e-08, 6.16657445107e-08, 2.26804019121e-07, 1.87337676039e-07, 5.52609868976e-08, 6.36835437717e-08, 2.63157406977e-08, 4.75074690698e-09, 7.47218675823e-10, 1.06544356671e-10, 1.03428099418e-10, 1.00571780071e-10, 9.79778688737e-11, 9.57188356354e-11, 9.3850066607e-11, 9.15859402206e-11, 9.00280058835e-11, 8.8719219471e-11, 8.76006420181e-11, 8.67785635017e-11, 8.63002724838e-11],
        "mean": [0.00104562006891, 0.00731705455109, 0.0114532932639, 0.00887443404645, 0.00670603103936, 0.0057205776684, 0.0045611881651, 0.00243741972372, 0.00085407786537, 0.00121978973038, 0.0012985492358, 0.00047191142221, 0.000249030068517, 0.000219800800551, 0.000261859153397, 0.000292520271614, 0.000136621601996, 8.42588196974e-05, 4.53226821264e-05, 5.49612486793e-05, 4.75440720038e-05, 4.2972391384e-05, 9.35538191698e-05, 0.000154450681293, 0.00012454634998, 2.05062315217e-05, 8.9640952865e-06, 8.68220195116e-06, 1.54618901433e-05, 2.60315664491e-05, 1.47847940752e-05, 7.0035553108e-06, 1.31186734507e-05, 3.56030318471e-06, 1.44792818446e-06, 1.45696992604e-06, 2.01771058528e-06, 4.33282684753e-06, 6.9296561378e-06, 5.89138426221e-06, 1.13885698738e-06, 1.94277890841e-06, 1.49697973484e-06, 1.59115415954e-06, 2.06032768801e-06, 1.18599029975e-06, 1.23427787457e-06, 3.34347532771e-07, 3.66585453548e-07, 1.57527927058e-06, 8.41567043608e-07, 7.64280628118e-07, 3.53815636345e-07, 1.90762207808e-07, 1.59218075169e-07, 3.74974433726e-07, 5.69145129248e-07, 4.10409938922e-07, 2.90037661443e-07, 8.68769021167e-08, 1.10827429012e-07, 1.04824941616e-07, 9.84274848292e-08, 8.5139312489e-08, 8.50139443287e-08, 6.62516086436e-08, 5.30770556395e-08, 4.21725268041e-08, 4.73287329328e-08, 3.56898368636e-08, 3.07191072579e-08, 2.30308110361e-08, 1.76452612521e-08, 1.85721980017e-08, 1.93160687445e-08, 1.99143936896e-08, 1.78834529407e-08, 2.09167705378e-08, 2.16753175408e-08, 2.01599892335e-08, 2.60113246497e-08, 1.97849736594e-08, 2.08424371095e-08, 1.94460749725e-08, 1.97881320219e-08, 2.11357384927e-08, 1.95581044693e-08, 1.80075225842e-08, 1.34506050742e-08, 1.28039179259e-08, 1.05760582514e-08, 1.28097772389e-08, 1.18537402116e-08, 1.06610738015e-08, 9.17735043515e-09, 8.91401796821e-09, 9.23734511105e-09, 9.86251347257e-09, 8.66256399945e-09, 7.19523152171e-09, 7.41653938263e-09, 5.87614223946e-09, 5.50853274106e-09, 4.81317119494e-09, 4.51869652807e-09, 5.07295228047e-09, 5.45291634069e-09, 4.42973924208e-09, 3.89716348081e-09, 4.91864415864e-09, 4.14585743513e-09, 2.08364570042e-09, 8.87991125076e-10, 3.65476315878e-10, 5.34154873111e-11, 1.12093225327e-11, 7.61222335166e-12, 7.41140395583e-12, 7.23571680003e-12, 7.03907244992e-12, 6.87102414895e-12, 6.75896144609e-12, 6.61925939408e-12, 6.4969141178e-12, 6.32796462799e-12, 6.10473520693e-12, 5.97519646608e-12, 5.93236007193e-12],
        "median": [0.000149050552864, 0.000635981094092, 0.0014337033499, 0.00216776644811, 0.00269881309941, 0.00171200023033, 0.00126401777379, 0.000677888398059, 0.000334802956786, 0.000414372480009, 0.000295144767733, 0.000176883928361, 0.000120269833133, 8.94362237887e-05, 5.51034536329e-05, 6.63440077915e-05, 5.00378264405e-05, 2.6803878427e-05, 1.8355618522e-05, 1.60191375471e-05, 1.03023476186e-05, 9.31301656237e-06, 1.24441376101e-05, 1.06749175757e-05, 9.30956593947e-06, 4.89709918838e-06, 1.69742168055e-06, 2.26125530389e-06, 2.28637441069e-06, 1.92325023818e-06, 1.44644855027e-06, 1.1157615063e-06, 1.30935450215e-06, 1.03528350337e-06, 4.95245899401e-07, 2.59399570268e-07, 4.75802892197e-07, 5.48985553905e-07, 8.27775238577e-07, 7.53513006657e-07, 3.38286383794e-07, 3.01252441659e-07, 1.73594017383e-07, 2.17345117903e-07, 4.26778910878e-07, 3.20459349723e-07, 2.3278900585e-07, 1.09468992093e-07, 8.64468461259e-08, 1.87902344351e-07, 3.33871639668e-07, 1.9981816024e-07, 4.63005989104e-08, 5.09361441914e-08, 3.58292737701e-08, 8.41458245304e-08, 8.1092025539e-08, 7.17760286761e-08, 5.38379225645e-08, 1.80248562742e-08, 2.43246223164e-08, 2.70126001567e-08, 2.44622455625e-08, 2.16515125828e-08, 1.60731623566e-08, 1.57719064475e-08, 1.6055357932e-08, 9.92207205286e-09, 1.22308971839e-08, 1.05684332397e-08, 9.92637172459e-09, 7.02303282196e-09, 5.01771912909e-09, 4.26834523282e-09, 5.67417224318e-09, 5.08310504799e-09, 5.05357267144e-09, 5.14000131346e-09, 5.42979883278e-09, 5.38860378541e-09, 7.09128089582e-09, 5.48575762593e-09, 6.49033005118e-09, 5.63819391175e-09, 6.56409593347e-09, 6.92958490589e-09, 5.36218980329e-09, 4.52642812121e-09, 3.15167092424e-09, 3.28290195029e-09, 3.3651903486e-09, 4.0164698234e-09, 4.14365741719e-09, 2.5978939e-09, 2.63005750512e-09, 2.20408358231e-09, 2.7056756835e-09, 2.88310575414e-09, 2.85969070646e-09, 2.40516007111e-09, 2.17917417444e-09, 1.59763158258e-09, 1.7598695834e-09, 1.68380109855e-09, 1.39052569459e-09, 1.49790890802e-09, 1.51108947577e-09, 1.12202047653e-09, 6.81905143463e-10, 6.28107232892e-10, 3.13344350467e-10, 1.75419470616e-10, 1.18305868574e-11, 2.96894626939e-12, 2.58123860827e-12, 2.39759340853e-12, 2.21086517149e-12, 2.20409844889e-12, 2.16453461058e-12, 2.06288566958e-12, 1.9657313971e-12, 1.9376015549e-12, 1.89717599269e-12, 1.93203699567e-12, 1.83688220884e-12, 1.64890735614e-12, 1.57247110298e-12, 1.55540868813e-12],
        "min": [6.94894712976e-24, 1.1086157335e-23, 2.00910014127e-23, 2.1538423912e-23, 1.23183391363e-23, 1.02587116652e-23, 1.22621493629e-23, 9.34435955607e-24, 3.02211804208e-24, 4.11402518885e-24, 1.24608413368e-23, 2.0389280765e-23, 2.66797743747e-23, 1.32869956414e-23, 2.1899390885e-23, 8.26550786006e-24, 5.59627037507e-24, 6.5745103568e-24, 8.09235052478e-24, 8.02923218604e-24, 1.7073507476e-23, 4.68768681128e-24, 9.92567667915e-25, 3.42974751814e-24, 9.73181963372e-24, 1.00133814457e-23, 3.41643509593e-24, 1.04176553047e-23, 7.57938188825e-24, 2.15995227668e-23, 2.69624926568e-23, 6.94113661794e-24, 3.34511852023e-24, 4.43458986174e-24, 4.17222261327e-24, 4.87766601372e-25, 1.21383329107e-24, 5.301755467e-24, 1.66198667016e-23, 1.50751902745e-23, 1.50507497859e-23, 8.65280148806e-24, 9.78267197425e-24, 7.8114379453e-24, 1.90795586699e-23, 5.36243188681e-24, 1.70523234053e-23, 1.17209892042e-23, 9.08487953852e-24, 1.32525539742e-23, 1.18669852697e-23, 2.40117111091e-23, 9.03841326462e-24, 2.77427297346e-23, 1.18677196992e-23, 1.29998818263e-23, 5.8652155402e-24, 5.98183205896e-24, 9.67198058976e-24, 8.70771015137e-24, 1.60553152393e-23, 7.82538185066e-24, 5.54014528825e-24, 6.4867716692e-24, 4.58683370556e-24, 2.89215892718e-24, 9.07532879954e-24, 9.53244923942e-24, 5.15205846061e-24, 1.75086273741e-23, 8.11108123812e-24, 6.5504256445e-24, 9.1415804938e-24, 9.71356539237e-24, 5.95432447919e-24, 1.06060100453e-23, 1.01141726259e-23, 1.00724395174e-23, 8.18746979501e-24, 5.92556339945e-24, 5.4385068715e-24, 4.4753747594e-24, 1.02790824204e-23, 1.62943274718e-23, 4.84564279691e-24, 1.53445594523e-23, 1.65443348476e-23, 6.63214059023e-24, 1.72844409935e-23, 1.2549467493e-23, 1.3771419346e-23, 1.41441750564e-23, 1.0542617183e-23, 6.44090887389e-24, 1.12611874261e-23, 1.26806534838e-23, 1.12720950059e-23, 1.01882135327e-23, 5.53370936655e-24, 8.20607113516e-24, 8.37992109031e-24, 8.60180005282e-24, 9.6659363375e-24, 1.59240408961e-23, 8.70856133229e-24, 1.21553959721e-23, 8.6303284186e-24, 1.1877747699e-23, 1.25559984724e-23, 1.18601048249e-23, 7.88496293711e-24, 6.78100574279e-24, 1.13355028566e-23, 1.33754805914e-23, 1.15040753323e-23, 9.01670854567e-24, 7.88358716369e-24, 1.42171604674e-23, 1.34057933605e-23, 1.42239020727e-23, 1.58230619671e-23, 1.00967301224e-23, 7.14361906851e-24, 7.11013823397e-24, 9.53883743503e-24, 1.12831067152e-23, 1.45996396773e-23, 1.18587124854e-23],
        "stdev": [0.0022509272676, 0.0153548941016, 0.0229458231479, 0.0168719496578, 0.0150970248505, 0.0140405995771, 0.0104723572731, 0.00556622166187, 0.00151034793817, 0.00263221957721, 0.00358294555917, 0.000793893181253, 0.000317096157232, 0.000319910293911, 0.000555597245693, 0.00089526415104, 0.000254633661825, 0.00013563039829, 6.50337315165e-05, 9.42062106333e-05, 9.43338527577e-05, 0.000108128224383, 0.000228571501793, 0.000389794411603, 0.000378005643142, 4.17650262534e-05, 2.82103646896e-05, 2.59746284428e-05, 3.44537766068e-05, 6.5135092882e-05, 3.98876072722e-05, 1.95625270862e-05, 4.23254314228e-05, 6.63439550408e-06, 3.07485879603e-06, 5.48168463865e-06, 6.23017422186e-06, 1.04096052382e-05, 1.68538463186e-05, 1.63556287589e-05, 2.19753019337e-06, 7.3145861279e-06, 4.80528024127e-06, 4.80715061713e-06, 4.03933108828e-06, 1.797249638e-06, 2.45231080953e-06, 6.48519119295e-07, 6.53696190511e-07, 3.4887318634e-06, 1.35130915169e-06, 1.28886017592e-06, 8.17990667201e-07, 4.49343048103e-07, 4.60083811049e-07, 9.05913907445e-07, 1.09446693841e-06, 9.8255713965e-07, 6.5881295086e-07, 2.22554817242e-07, 3.41826222439e-07, 2.90890227461e-07, 2.30503431453e-07, 1.73983451646e-07, 1.85440569567e-07, 1.48338145323e-07, 1.01137494823e-07, 9.20083635947e-08, 9.38339255185e-08, 7.91334571204e-08, 5.87092792159e-08, 4.6201847681e-08, 3.74576742956e-08, 4.87983342623e-08, 4.81489763615e-08, 5.10257933684e-08, 3.72744750621e-08, 5.29500212565e-08, 5.3280604817e-08, 4.5228304657e-08, 6.12349282392e-08, 4.1114137872e-08, 4.3012484241e-08, 4.68708236667e-08, 4.43721859256e-08, 3.75653144147e-08, 3.93533703402e-08, 3.7359633609e-08, 3.19417559069e-08, 3.07106766684e-08, 2.48735894104e-08, 3.05621838947e-08, 2.38298500932e-08, 2.46561349115e-08, 1.79469523687e-08, 2.35180461772e-08, 1.96116971551e-08, 2.21293134928e-08, 1.56635806547e-08, 1.31606396891e-08, 1.59024455826e-08, 1.17656320242e-08, 1.08571791557e-08, 9.19641074404e-09, 9.65997326574e-09, 9.62188551057e-09, 9.68126023793e-09, 9.49575973408e-09, 9.07661146243e-09, 1.54035983968e-08, 1.29464439169e-08, 5.52518830688e-09, 4.83056350475e-09, 2.23719021086e-09, 3.4575706187e-10, 4.56762266898e-11, 1.35309862273e-11, 1.3140442727e-11, 1.27786843607e-11, 1.24477103972e-11, 1.21672455097e-11, 1.19173880833e-11, 1.16658635876e-11, 1.14662359468e-11, 1.13024754486e-11, 1.11677802422e-11, 1.10713530357e-11, 1.10118685004e-11],
        "var": [5.06667402078e-06, 0.000235772764427, 0.000526510761119, 0.000284662673948, 0.00022792017262, 0.000197138448129, 0.000109670261736, 3.09828246827e-05, 2.28115072787e-06, 6.92858020557e-06, 1.28374986161e-05, 6.30266356438e-07, 1.00549968352e-07, 1.02342589514e-07, 3.08688271389e-07, 8.01497947123e-07, 6.48382965096e-08, 1.83956032629e-08, 4.2293866187e-09, 8.87481022005e-09, 8.89887630251e-09, 1.1691712487e-08, 5.22449283835e-08, 1.51939673287e-07, 1.42888268329e-07, 1.74431746824e-09, 7.9582468393e-10, 6.74681310819e-10, 1.18706267038e-09, 4.24258006504e-09, 1.59102120367e-09, 3.82692433298e-10, 1.79144221679e-09, 4.4015201206e-11, 9.45475642222e-12, 3.00488661731e-11, 3.88150692143e-11, 1.08359883566e-10, 2.84052142918e-10, 2.67506572449e-10, 4.82913882494e-12, 5.35031706439e-11, 2.30907185733e-11, 2.31086955127e-11, 1.63161966577e-11, 3.23010628661e-12, 6.01382832421e-12, 4.20577066012e-13, 4.27318716436e-13, 1.21712492515e-11, 1.82603628399e-12, 1.66116046699e-12, 6.69108702906e-13, 2.01909181648e-13, 2.11677111386e-13, 8.20680058199e-13, 1.19785800202e-12, 9.65418608771e-13, 4.34034508638e-13, 4.95306480021e-14, 1.1684517286e-13, 8.46171209815e-14, 5.31318289062e-14, 3.02702436413e-14, 3.43882061227e-14, 2.20042049631e-14, 1.02287927409e-14, 8.46553865419e-15, 8.80480584275e-15, 6.26210399114e-15, 3.44677950325e-15, 2.13461069499e-15, 1.40307736048e-15, 2.3812774889e-15, 2.31832388268e-15, 2.60363168437e-15, 1.38938655519e-15, 2.80370488992e-15, 2.83882287591e-15, 2.0455993907e-15, 3.74971617816e-15, 1.69037240734e-15, 1.85007390504e-15, 2.19687418112e-15, 1.96889081644e-15, 1.41115286672e-15, 1.54868782983e-15, 1.39574216104e-15, 1.0202758548e-15, 9.43145564021e-16, 6.18695416927e-16, 9.34047053739e-16, 5.67861793388e-16, 6.07924969486e-16, 3.2209309263e-16, 5.53098485574e-16, 3.84618682516e-16, 4.89706539801e-16, 2.45347751853e-16, 1.73202435255e-16, 2.52887747982e-16, 1.38430091644e-16, 1.17878332721e-16, 8.45739766172e-17, 9.33150853176e-17, 9.25806812826e-17, 9.3726802887e-17, 9.0169449797e-17, 8.2384879522e-17, 2.37270816245e-16, 1.67610403147e-16, 3.05277060025e-17, 2.33343448724e-17, 5.0050204916e-18, 1.19547954912e-19, 2.08631772787e-21, 1.83087598395e-22, 1.72671226567e-22, 1.63294775361e-22, 1.54945484162e-22, 1.48041865768e-22, 1.42024144482e-22, 1.36092377481e-22, 1.31474562446e-22, 1.27745951425e-22, 1.24719313012e-22, 1.22574860906e-22, 1.21261249726e-22]
    },
    "mfcc": {
        "mean": [-824.479614258, 216.659820557, 49.5498657227, 26.2667484283, 23.5457057953, 13.4577226639, -1.93873918056, 5.83999490738, 2.83789372444, 4.17293405533, 3.79318714142, -2.72975254059, -1.76480877399],
        "cov": [[7280.0390625, 575.535400391, -404.996704102, -32.2166671753, -126.946624756, -63.4596176147, -56.746257782, 173.593994141, -95.6898880005, -165.922286987, -54.9451942444, 66.7543106079, 64.41040802], [575.535400391, 1210.9486084, 77.5422973633, 32.0223007202, 157.437911987, 13.9336957932, -2.56484270096, 30.1491203308, 44.1675605774, 19.8241710663, 15.322306633, 5.83670949936, -7.20564842224], [-404.996704102, 77.5422973633, 697.881347656, 125.242263794, -5.86266613007, 71.2217025757, 49.6394195557, -35.9946861267, -14.031085968, 35.2099227905, 16.1003856659, -6.41053295135, -5.65871334076], [-32.2166671753, 32.0223007202, 125.242263794, 175.897888184, 32.17370224, 16.3315868378, 24.3794784546, 8.78292179108, 15.956823349, 39.3913612366, 25.0389213562, 8.58599758148, 0.251345455647], [-126.946624756, 157.437911987, -5.86266613007, 32.17370224, 134.620788574, 58.5029220581, 16.1765937805, 15.1066083908, 34.7612380981, 13.8223276138, -2.07428479195, -4.11769676208, 13.2276821136], [-63.4596176147, 13.9336957932, 71.2217025757, 16.3315868378, 58.5029220581, 131.334991455, 54.5478935242, 9.09446239471, 0.12591893971, -13.8411016464, -19.9768733978, -10.9156141281, 24.8505268097], [-56.746257782, -2.56484270096, 49.6394195557, 24.3794784546, 16.1765937805, 54.5478935242, 84.6460266113, 41.3643074036, 6.95243215561, -11.7194690704, -8.42346191406, 1.9968996048, 14.4620428085], [173.593994141, 30.1491203308, -35.9946861267, 8.78292179108, 15.1066083908, 9.09446239471, 41.3643074036, 82.6195144653, 30.9358520508, -12.2085132599, -0.337636202574, 14.6089487076, 4.4429063797], [-95.6898880005, 44.1675605774, -14.031085968, 15.956823349, 34.7612380981, 0.12591893971, 6.95243215561, 30.9358520508, 75.9368438721, 50.8247299194, 28.2192935944, 11.6087331772, -5.12921047211], [-165.922286987, 19.8241710663, 35.2099227905, 39.3913612366, 13.8223276138, -13.8411016464, -11.7194690704, -12.2085132599, 50.8247299194, 107.988731384, 64.0516586304, 11.47260952, -6.20096731186], [-54.9451942444, 15.322306633, 16.1003856659, 25.0389213562, -2.07428479195, -19.9768733978, -8.42346191406, -0.337636202574, 28.2192935944, 64.0516586304, 82.213142395, 28.5905704498, -2.18990397453], [66.7543106079, 5.83670949936, -6.41053295135, 8.58599758148, -4.11769676208, -10.9156141281, 1.9968996048, 14.6089487076, 11.6087331772, 11.47260952, 28.5905704498, 46.5366439819, 19.9700069427], [64.41040802, -7.20564842224, -5.65871334076, 0.251345455647, 13.2276821136, 24.8505268097, 14.4620428085, 4.4429063797, -5.12921047211, -6.20096731186, -2.18990397453, 19.9700069427, 57.4488830566]],
        "icov": [[0.000189988990314, -0.000144034725963, 0.00011080049444, -0.000155348170665, 0.000439434457803, -0.000266852992354, 0.000568236631807, -0.000745860452298, 0.000403698533773, -9.90854096017e-06, 6.6261702159e-05, -6.44665124128e-05, -0.000230687146541], [-0.000144034725963, 0.00115752359852, -0.000347148947185, 0.000345755775925, -0.00197040452622, 0.000789484241977, -0.00022557763441, 9.9805132777e-05, -2.8137854315e-05, 7.95758605818e-05, -0.000218912711716, -0.000145277372212, 0.000480449933093], [0.00011080049444, -0.000347148947185, 0.00208408082835, -0.00140740617644, 0.00140728999395, -0.00138553313445, -0.000835413637105, 0.00112179643475, 0.000324610940879, -0.000416652765125, 0.00014323151845, -0.00039615231799, 0.000569702882785], [-0.000155348170665, 0.000345755775925, -0.00140740617644, 0.00800222717226, -0.00310298078693, 0.00136813719291, -0.00222980650142, -0.000861072621774, 0.00213714851998, -0.00337244290859, 5.72206481593e-05, -0.0012727258727, 0.0010658634128], [0.000439434457803, -0.00197040452622, 0.00140728999395, -0.00310298078693, 0.0156648959965, -0.0074523743242, 0.00379810179584, -0.00106888788287, -0.00595838343725, 0.00104459712747, 0.000634662574157, 0.00234314613044, -0.00305384700187], [-0.000266852992354, 0.000789484241977, -0.00138553313445, 0.00136813719291, -0.0074523743242, 0.0164218414575, -0.0100256055593, 0.00405761320144, -0.000499241810758, 0.0014662775211, -6.78457872709e-05, 0.00376138859428, -0.00411826744676], [0.000568236631807, -0.00022557763441, -0.000835413637105, -0.00222980650142, 0.00379810179584, -0.0100256055593, 0.0269617699087, -0.0158407334238, 0.0033224336803, -0.000811088364571, 0.000386789179174, 0.00183950853534, -0.00325351185165], [-0.000745860452298, 9.9805132777e-05, 0.00112179643475, -0.000861072621774, -0.00106888788287, 0.00405761320144, -0.0158407334238, 0.0305137429386, -0.0167237464339, 0.0108474902809, -0.00190123647917, -0.00505447247997, 0.00244406959973], [0.000403698533773, -2.8137854315e-05, 0.000324610940879, 0.00213714851998, -0.00595838343725, -0.000499241810758, 0.0033224336803, -0.0167237464339, 0.0349753573537, -0.0195297691971, 0.00472543248907, -0.0052648182027, 0.00463627278805], [-9.90854096017e-06, 7.95758605818e-05, -0.000416652765125, -0.00337244290859, 0.00104459712747, 0.0014662775211, -0.000811088364571, 0.0108474902809, -0.0195297691971, 0.0312561988831, -0.019080510363, 0.00797596853226, -0.00338451284915], [6.6261702159e-05, -0.000218912711716, 0.00014323151845, 5.72206481593e-05, 0.000634662574157, -6.78457872709e-05, 0.000386789179174, -0.00190123647917, 0.00472543248907, -0.019080510363, 0.0318556912243, -0.0179068837315, 0.00564635032788], [-6.44665124128e-05, -0.000145277372212, -0.00039615231799, -0.0012727258727, 0.00234314613044, 0.00376138859428, 0.00183950853534, -0.00505447247997, -0.0052648182027, 0.00797596853226, -0.0179068837315, 0.0420791581273, -0.0171371605247], [-0.000230687146541, 0.000480449933093, 0.000569702882785, 0.0010658634128, -0.00305384700187, -0.00411826744676, -0.00325351185165, 0.00244406959973, 0.00463627278805, -0.00338451284915, 0.00564635032788, -0.0171371605247, 0.0271126925945]]
    },
    "spectral_contrast_coeffs": {
        "dmean": [0.0596000775695, 0.0470462068915, 0.0388702973723, 0.0299768615514, 0.0213404130191, 0.0178189575672],
        "dmean2": [0.0988437980413, 0.0797597691417, 0.0633111298084, 0.0461549013853, 0.0333828367293, 0.0295195654035],
        "dvar": [0.00212738197297, 0.00140340300277, 0.00106551451609, 0.000615380879026, 0.000326715729898, 0.000222421032959],
        "dvar2": [0.00508156744763, 0.0037658137735, 0.00260565755889, 0.00130736001302, 0.000740789750125, 0.000520523695741],
        "max": [-0.522832632065, -0.544642806053, -0.59895670414, -0.676975667477, -0.742642223835, -0.734779238701],
        "mean": [-0.717128574848, -0.755266070366, -0.79052656889, -0.810161173344, -0.842323362827, -0.834368765354],
        "median": [-0.722971200943, -0.759271621704, -0.805138170719, -0.814003586769, -0.849494457245, -0.836616516113],
        "min": [-0.9650182724, -0.966315746307, -0.966670691967, -0.955941200256, -0.955731391907, -0.958534777164],
        "stdev": [0.0707252174616, 0.0671400055289, 0.0653662011027, 0.0522744208574, 0.0364656560123, 0.0238477177918],
        "var": [0.00500205671415, 0.00450778054073, 0.00427273986861, 0.0027326149866, 0.00132974400185, 0.000568713643588]
    },
    "spectral_contrast_valleys": {
        "dmean": [0.514857411385, 0.549696266651, 0.581263780594, 0.560601294041, 0.545982599258, 0.52660048008],
        "dmean2": [0.746211290359, 0.818824410439, 0.853160500526, 0.800549149513, 0.741597771645, 0.738124907017],
        "dvar": [0.734806418419, 0.772913634777, 0.739747226238, 0.625117361546, 0.572669625282, 0.460938483477],
        "dvar2": [0.656711161137, 0.750143289566, 0.823753893375, 0.655232429504, 0.59528106451, 0.508659601212],
        "max": [-4.742374897, -5.68395900726, -6.71389245987, -7.45429134369, -8.13612174988, -10.4388246536],
        "mean": [-6.32220840454, -7.35734128952, -8.9222984314, -9.62549972534, -10.2553405762, -12.5112628937],
        "median": [-6.13686418533, -7.20648479462, -8.82508850098, -9.49772071838, -10.1527433395, -12.4454298019],
        "min": [-26.959192276, -27.4998321533, -27.1935482025, -27.5293769836, -27.2981624603, -27.2651615143],
        "stdev": [1.48742175102, 1.43182134628, 1.38110363483, 1.39463889599, 1.34688460827, 1.21212482452],
        "var": [2.21242332458, 2.05011248589, 1.90744721889, 1.94501769543, 1.81409800053, 1.46924650669]
    }
},
"rhythm": {
    "beats_count": 19,
    "beats_loudness": {
        "dmean": 0.0575659126043,
        "dmean2": 0.0801448822021,
        "dvar": 0.0021308476571,
        "dvar2": 0.00476510962471,
        "max": 0.283742159605,
        "mean": 0.188832163811,
        "median": 0.204469904304,
        "min": 0.0109553439543,
        "stdev": 0.0749972164631,
        "var": 0.00562458205968
    },
    "bpm": 144.140625,
    "bpm_histogram_first_peak_bpm": 144,
    "bpm_histogram_first_peak_weight": 0.142857134342,
    "bpm_histogram_second_peak_bpm": 152,
    "bpm_histogram_second_peak_spread": 0,
    "bpm_histogram_second_peak_weight": 0.111111111939,
    "danceability": 1.65966248512,
    "onset_rate": 6.98037242889,
    "beats_loudness_band_ratio": {
        "dmean": [0.0443280786276, 0.0424016490579, 0.0128978276625, 0.000799318950158, 0.000150757012307, 1.06904954009e-05],
        "dmean2": [0.0591020025313, 0.0544116050005, 0.0230022072792, 0.00129538693, 0.000236972569837, 1.4873753571e-05],
        "dvar": [0.00669705774635, 0.00493312301114, 0.000225547060836, 9.18479315715e-07, 4.0619202224e-08, 1.425443652e-10],
        "dvar2": [0.00587882753462, 0.00378267560154, 0.000319198763464, 2.56913699559e-06, 5.09365598589e-08, 2.01295979885e-10],
        "max": [0.989586114883, 0.377701044083, 0.0660688728094, 0.00445014704019, 0.000943696126342, 5.8237092162e-05],
        "mean": [0.941462337971, 0.0549214817584, 0.0109501667321, 0.000978061696514, 0.000250374811003, 1.42362705446e-05],
        "median": [0.961192190647, 0.0359900668263, 0.00592661323026, 0.000519178924151, 0.0002335512836, 1.16613373393e-05],
        "min": [0.577481687069, 0.00895697064698, 0.000518835324328, 7.09367304808e-05, 7.03643399902e-06, 3.67522852684e-06],
        "stdev": [0.0879128500819, 0.0792020484805, 0.0154164312407, 0.00109942990821, 0.000225302050239, 1.33515941343e-05],
        "var": [0.00772866979241, 0.00627296464518, 0.000237666346948, 1.20874608456e-06, 5.07610167233e-08, 1.78265055495e-10]
    },
    "beats_position": [0.359909296036, 0.719818592072, 1.09133780003, 1.50929701328, 1.92725622654, 2.34521532059, 2.76317453384, 3.16952371597, 3.5758728981, 3.99383211136, 4.41179132462, 4.82975053787, 5.22448968887, 5.64244890213, 6.03718805313, 6.45514726639, 6.87310647964, 7.2910656929, 7.70902490616],
    "bpm_histogram": [0, 0, 0, 0, 0, 0, 0, 0, 0, 0, 0, 0, 0, 0, 0, 0, 0, 0, 0, 0, 0, 0, 0, 0, 0, 0, 0, 0, 0, 0, 0, 0, 0, 0, 0, 0, 0, 0, 0, 0, 0, 0, 0, 0, 0, 0, 0, 0, 0, 0, 0, 0, 0, 0, 0, 0, 0, 0, 0, 0, 0, 0, 0, 0, 0, 0, 0, 0, 0, 0, 0, 0, 0, 0, 0, 0, 0, 0, 0, 0, 0, 0, 0, 0, 0, 0, 0, 0, 0, 0, 0, 0, 0, 0, 0, 0, 0, 0, 0, 0, 0, 0, 0, 0, 0, 0, 0, 0, 0, 0, 0, 0, 0, 0, 0, 0, 0, 0, 0, 0, 0, 0, 0, 0, 0, 0, 0, 0, 0, 0, 0, 0, 0, 0, 0, 0, 0, 0, 0, 0, 0, 0, 0, 0, 0.666666686535, 0, 0, 0, 0.111111111939, 0, 0, 0, 0.111111111939, 0, 0, 0, 0, 0, 0, 0, 0, 0.0555555559695, 0, 0, 0, 0, 0, 0.0555555559695, 0, 0, 0, 0, 0, 0, 0, 0, 0, 0, 0, 0, 0, 0, 0, 0, 0, 0, 0, 0, 0, 0, 0, 0, 0, 0, 0, 0, 0, 0, 0, 0, 0, 0, 0, 0, 0, 0, 0, 0, 0, 0, 0, 0, 0, 0, 0, 0, 0, 0, 0, 0, 0, 0, 0, 0, 0, 0, 0, 0, 0, 0, 0, 0, 0, 0, 0, 0, 0, 0, 0, 0, 0, 0, 0, 0, 0, 0, 0, 0, 0, 0]
},
"tonal": {
    "chords_changes_rate": 0.155172407627,
    "chords_number_rate": 0.0402298867702,
    "chords_strength": {
        "dmean": 0.0144605757669,
        "dmean2": 0.0173242650926,
        "dvar": 0.000119837670354,
        "dvar2": 0.000172013431438,
        "max": 0.554830372334,
        "mean": 0.45016014576,
        "median": 0.446993470192,
        "min": 0.355198681355,
        "stdev": 0.051299829036,
        "var": 0.0026316724252
    },
    "hpcp_crest": {
        "dmean": 4.60108709335,
        "dmean2": 8.13396453857,
        "dvar": 12.3962078094,
        "dvar2": 31.8332271576,
        "max": 35.8105545044,
        "mean": 12.5968055725,
        "median": 11.8541240692,
        "min": 0,
        "stdev": 4.45540618896,
        "var": 19.8506450653
    },
    "hpcp_entropy": {
        "dmean": 0.617800354958,
        "dmean2": 1.06527256966,
        "dvar": 0.185721293092,
        "dvar2": 0.572290062904,
        "max": 3.48664283752,
        "mean": 1.95878481865,
        "median": 1.96011066437,
        "min": 0,
        "stdev": 0.56787699461,
        "var": 0.322484254837
    },
    "key_edma": {
        "strength": 0.644197642803,
        "key": "C#",
        "scale": "minor"
    },
    "key_krumhansl": {
        "strength": 0.639910101891,
        "key": "C#",
        "scale": "minor"
    },
    "key_temperley": {
        "strength": 0.632256805897,
        "key": "C#",
        "scale": "minor"
    },
    "tuning_diatonic_strength": 0.511076271534,
    "tuning_equal_tempered_deviation": 0.310436517,
    "tuning_frequency": 455.516601562,
    "tuning_nontempered_energy_ratio": 0.929745793343,
    "hpcp": {
        "dmean": [0.14367634058, 0.147130519152, 0.1323800385, 0.0984271913767, 0.0995177552104, 0.132757693529, 0.130532965064, 0.109172314405, 0.0821070000529, 0.069210126996, 0.108191981912, 0.142680555582, 0.162871465087, 0.22189502418, 0.232188850641, 0.210724294186, 0.139954805374, 0.13844037056, 0.149673908949, 0.177487075329, 0.161663398147, 0.128323718905, 0.0989382192492, 0.0967700704932, 0.0850901827216, 0.0499173216522, 0.0508145913482, 0.095049738884, 0.133601561189, 0.127334490418, 0.123143211007, 0.235951989889, 0.297373592854, 0.304237514734, 0.267008066177, 0.237667769194],
        "dmean2": [0.268822103739, 0.265318542719, 0.237452507019, 0.175635278225, 0.186759546399, 0.250689029694, 0.252532809973, 0.204144924879, 0.159787669778, 0.135383158922, 0.205733969808, 0.265968680382, 0.306130707264, 0.414006799459, 0.406513959169, 0.384404033422, 0.257532268763, 0.26039686799, 0.281663656235, 0.309031605721, 0.279078930616, 0.242201268673, 0.184440329671, 0.182447880507, 0.166588962078, 0.0959580913186, 0.0984088331461, 0.187266990542, 0.254620850086, 0.246202245355, 0.225193873048, 0.440108716488, 0.547760784626, 0.550285279751, 0.48245537281, 0.428048729897],
        "dvar": [0.0602626800537, 0.065899707377, 0.0581405796111, 0.0371172279119, 0.0325963646173, 0.0572866760194, 0.0632704049349, 0.0467435307801, 0.0322360247374, 0.0238364990801, 0.05362540856, 0.0689412429929, 0.0826809108257, 0.0898350253701, 0.0787452161312, 0.0778025686741, 0.0533722788095, 0.0629978179932, 0.0628746971488, 0.068217895925, 0.0621028617024, 0.0529740005732, 0.0410701371729, 0.0484081543982, 0.0421922840178, 0.0177756715566, 0.0118443211541, 0.0414120219648, 0.0675904750824, 0.0625345110893, 0.0441032797098, 0.104859292507, 0.112620763481, 0.101092509925, 0.0992877855897, 0.0940195173025],
        "dvar2": [0.160815343261, 0.172367036343, 0.127100765705, 0.0989150926471, 0.0915056094527, 0.167896941304, 0.189856752753, 0.134738445282, 0.0917746499181, 0.0694092586637, 0.164072409272, 0.198613852262, 0.243133693933, 0.275695115328, 0.210329279304, 0.213873311877, 0.132799014449, 0.159690782428, 0.167366251349, 0.164978742599, 0.154128536582, 0.161826357245, 0.111006893218, 0.138314262033, 0.121999442577, 0.0513976216316, 0.0341554284096, 0.121503286064, 0.199387565255, 0.177016943693, 0.117705591023, 0.26896739006, 0.309796243906, 0.243089184165, 0.23011893034, 0.254815220833],
        "max": [1, 1, 1, 1, 1, 1, 1, 1, 1, 1, 1, 1, 1, 1, 1, 1, 1, 1, 1, 1, 1, 1, 1, 0.984152019024, 1, 0.833849728107, 0.584482192993, 1, 1, 1, 1, 1, 1, 1, 1, 1],
        "mean": [0.0913912206888, 0.11541852355, 0.127332746983, 0.0742894262075, 0.0636173039675, 0.0820382237434, 0.0799604430795, 0.0668010413647, 0.0464975871146, 0.0374623835087, 0.0626198127866, 0.0888182446361, 0.106806844473, 0.149425193667, 0.186090692878, 0.148805812001, 0.102709449828, 0.0897723808885, 0.105545319617, 0.168920770288, 0.150418534875, 0.0830022320151, 0.0602035671473, 0.057927377522, 0.0477584972978, 0.0313492938876, 0.0308277625591, 0.0530785694718, 0.0795381069183, 0.0710806101561, 0.0780980959535, 0.153630509973, 0.215251728892, 0.256792932749, 0.268807381392, 0.174861520529],
        "median": [0.00615952815861, 0.00130454474129, 0.000979565200396, 0.00565837090835, 0.00807004421949, 0.0108803417534, 0.00594841782004, 0.00326019059867, 0.00168450875208, 0.000867157592438, 0.000865765265189, 0.00264597032219, 0.00396793987602, 0.0167434569448, 0.0396719276905, 0.0208878554404, 0.00828151777387, 0.00231564976275, 0.00257237278856, 0.0282520838082, 0.0285130552948, 0.0114275161177, 0.00304264761508, 0.00161231774837, 0.00146905856673, 0.00191228557378, 0.00183248147368, 0.00202425941825, 0.00390962604433, 0.0042366636917, 0.00240821391344, 0.0062421252951, 0.0397366285324, 0.0539085753262, 0.0444337129593, 0.0257396325469],
        "min": [0, 0, 0, 0, 0, 0, 0, 0, 0, 0, 0, 0, 0, 0, 0, 0, 0, 0, 0, 0, 0, 0, 0, 0, 0, 0, 0, 0, 0, 0, 0, 0, 0, 0, 0, 0],
        "stdev": [0.207512661815, 0.248059570789, 0.274392992258, 0.178083300591, 0.145156592131, 0.192556872964, 0.198721930385, 0.170924812555, 0.135689884424, 0.116383567452, 0.18103851378, 0.221160486341, 0.247195377946, 0.273529440165, 0.27554538846, 0.249438986182, 0.218652039766, 0.220785394311, 0.235501930118, 0.282781332731, 0.268183916807, 0.186625033617, 0.162532955408, 0.168998584151, 0.154009386897, 0.102754369378, 0.0848999917507, 0.15445818007, 0.204720959067, 0.192032456398, 0.182126581669, 0.290523290634, 0.319608658552, 0.348642647266, 0.360794097185, 0.291184574366],
        "var": [0.0430615060031, 0.0615335479379, 0.0752915069461, 0.0317136608064, 0.0210704356432, 0.0370781496167, 0.0394904054701, 0.0292152911425, 0.018411744386, 0.0135451350361, 0.0327749438584, 0.0489119589329, 0.0611055530608, 0.0748183503747, 0.0759252533317, 0.0622198060155, 0.047808714211, 0.0487461872399, 0.0554611608386, 0.0799652785063, 0.0719226077199, 0.0348289012909, 0.0264169629663, 0.0285605229437, 0.0237188916653, 0.0105584599078, 0.0072080087848, 0.0238573271781, 0.0419106706977, 0.0368764661252, 0.0331700928509, 0.0844037905335, 0.102149687707, 0.121551692486, 0.130172371864, 0.0847884565592]
    },
    "chords_histogram": [18.3908042908, 0, 41.9540214539, 0, 0, 0, 0, 0, 0, 1.14942526817, 0, 6.89655160904, 0, 0, 0, 0, 0, 0, 6.32183885574, 24.1379318237, 0, 0, 0, 1.14942526817],
    "thpcp": [1, 0.650508642197, 0.339987754822, 0.429372608662, 0.473695129156, 0.276366770267, 0.236665025353, 0.305193334818, 0.297463715076, 0.248508960009, 0.172977343202, 0.139365166426, 0.232954218984, 0.330415934324, 0.397335976362, 0.555882036686, 0.692282676697, 0.553577840328, 0.38209310174, 0.333965450525, 0.392642945051, 0.628408253193, 0.559577405453, 0.308779597282, 0.223965451121, 0.215497717261, 0.177668109536, 0.11662363261, 0.11468346417, 0.197459489107, 0.295892566442, 0.264429539442, 0.290535539389, 0.571526408195, 0.800765693188, 0.95530462265],
    "chords_key": "Ab",
    "chords_scale": "minor"
}
}